{
"meta":{"test_sets":[],"test_metrics":[],"learn_metrics":[{"best_value":"Min","name":"RMSE"}],"launch_mode":"Train","parameters":"","iteration_count":1000,"learn_sets":["learn"],"name":"experiment"},
"iterations":[
{"learn":[217.687953],"iteration":0,"passed_time":0.00198974832,"remaining_time":1.987758572},
{"learn":[212.1025015],"iteration":1,"passed_time":0.003569271629,"remaining_time":1.781066543},
{"learn":[206.3938432],"iteration":2,"passed_time":0.004748565101,"remaining_time":1.578106469},
{"learn":[200.8107139],"iteration":3,"passed_time":0.006130575587,"remaining_time":1.526513321},
{"learn":[195.6936723],"iteration":4,"passed_time":0.007468572233,"remaining_time":1.486245874},
{"learn":[190.2563376],"iteration":5,"passed_time":0.008871683048,"remaining_time":1.469742158},
{"learn":[185.2989936],"iteration":6,"passed_time":0.01006188632,"remaining_time":1.427350445},
{"learn":[180.7049253],"iteration":7,"passed_time":0.01126361546,"remaining_time":1.396688316},
{"learn":[176.2810379],"iteration":8,"passed_time":0.01248463209,"remaining_time":1.374696712},
{"learn":[171.9673581],"iteration":9,"passed_time":0.01370258522,"remaining_time":1.356555937},
{"learn":[167.5699563],"iteration":10,"passed_time":0.01513189127,"remaining_time":1.360494588},
{"learn":[163.6272109],"iteration":11,"passed_time":0.01666583077,"remaining_time":1.3721534},
{"learn":[159.8826216],"iteration":12,"passed_time":0.01802405669,"remaining_time":1.368441842},
{"learn":[156.3784768],"iteration":13,"passed_time":0.01930032875,"remaining_time":1.359294582},
{"learn":[152.6602528],"iteration":14,"passed_time":0.02045500517,"remaining_time":1.343212006},
{"learn":[148.9636108],"iteration":15,"passed_time":0.0216721683,"remaining_time":1.332838351},
{"learn":[145.1689163],"iteration":16,"passed_time":0.02284395049,"remaining_time":1.320917843},
{"learn":[141.8942165],"iteration":17,"passed_time":0.02408714922,"remaining_time":1.314087807},
{"learn":[137.9796202],"iteration":18,"passed_time":0.02536392448,"remaining_time":1.309579469},
{"learn":[134.5952717],"iteration":19,"passed_time":0.0265277036,"remaining_time":1.299857476},
{"learn":[131.6519348],"iteration":20,"passed_time":0.0276441875,"remaining_time":1.288745693},
{"learn":[128.4499055],"iteration":21,"passed_time":0.02885382935,"remaining_time":1.282683868},
{"learn":[125.3464832],"iteration":22,"passed_time":0.0301124028,"remaining_time":1.279122502},
{"learn":[122.5654435],"iteration":23,"passed_time":0.03134760847,"remaining_time":1.274802744},
{"learn":[119.7920725],"iteration":24,"passed_time":0.0326246673,"remaining_time":1.272362025},
{"learn":[117.1662386],"iteration":25,"passed_time":0.03380952067,"remaining_time":1.266556659},
{"learn":[114.1999667],"iteration":26,"passed_time":0.03437195576,"remaining_time":1.238663443},
{"learn":[111.4231022],"iteration":27,"passed_time":0.03555294063,"remaining_time":1.234194939},
{"learn":[108.9608638],"iteration":28,"passed_time":0.03677135374,"remaining_time":1.231206362},
{"learn":[106.7395394],"iteration":29,"passed_time":0.03797300038,"remaining_time":1.227793679},
{"learn":[104.6726045],"iteration":30,"passed_time":0.03910926642,"remaining_time":1.222479973},
{"learn":[102.5352039],"iteration":31,"passed_time":0.04040058606,"remaining_time":1.222117728},
{"learn":[100.5302795],"iteration":32,"passed_time":0.04159972096,"remaining_time":1.218997884},
{"learn":[98.66298995],"iteration":33,"passed_time":0.04288057436,"remaining_time":1.218312789},
{"learn":[96.726186],"iteration":34,"passed_time":0.04410399667,"remaining_time":1.216010194},
{"learn":[94.42967147],"iteration":35,"passed_time":0.04536366725,"remaining_time":1.214738201},
{"learn":[92.38744743],"iteration":36,"passed_time":0.0465228143,"remaining_time":1.210850545},
{"learn":[90.58893988],"iteration":37,"passed_time":0.04772762016,"remaining_time":1.208262384},
{"learn":[88.58664745],"iteration":38,"passed_time":0.04898551363,"remaining_time":1.207053297},
{"learn":[86.88150228],"iteration":39,"passed_time":0.05024294353,"remaining_time":1.205830645},
{"learn":[85.19094771],"iteration":40,"passed_time":0.05145744743,"remaining_time":1.203602246},
{"learn":[83.30070508],"iteration":41,"passed_time":0.05267771873,"remaining_time":1.20155368},
{"learn":[81.65265592],"iteration":42,"passed_time":0.05447778266,"remaining_time":1.212447395},
{"learn":[79.98708158],"iteration":43,"passed_time":0.05605148928,"remaining_time":1.217845994},
{"learn":[78.59550622],"iteration":44,"passed_time":0.05749225298,"remaining_time":1.220113369},
{"learn":[77.11258891],"iteration":45,"passed_time":0.0587154453,"remaining_time":1.217707279},
{"learn":[75.72276284],"iteration":46,"passed_time":0.0598890803,"remaining_time":1.214346671},
{"learn":[74.36379649],"iteration":47,"passed_time":0.06108007927,"remaining_time":1.211421572},
{"learn":[72.87799004],"iteration":48,"passed_time":0.06229998772,"remaining_time":1.209128333},
{"learn":[71.36493326],"iteration":49,"passed_time":0.0635595658,"remaining_time":1.20763175},
{"learn":[69.84101716],"iteration":50,"passed_time":0.06478440844,"remaining_time":1.20549811},
{"learn":[68.78409311],"iteration":51,"passed_time":0.06609337204,"remaining_time":1.204933013},
{"learn":[67.62661646],"iteration":52,"passed_time":0.0673094177,"remaining_time":1.202679596},
{"learn":[66.48299785],"iteration":53,"passed_time":0.06863147642,"remaining_time":1.202321791},
{"learn":[65.24560148],"iteration":54,"passed_time":0.06998405495,"remaining_time":1.202453308},
{"learn":[63.83292344],"iteration":55,"passed_time":0.07117656496,"remaining_time":1.199833524},
{"learn":[62.60174615],"iteration":56,"passed_time":0.07238733286,"remaining_time":1.197565875},
{"learn":[61.72539502],"iteration":57,"passed_time":0.07364146747,"remaining_time":1.196039006},
{"learn":[60.54561269],"iteration":58,"passed_time":0.07502797716,"remaining_time":1.196632653},
{"learn":[59.3931629],"iteration":59,"passed_time":0.07621231054,"remaining_time":1.193992865},
{"learn":[58.34175079],"iteration":60,"passed_time":0.07744778405,"remaining_time":1.19218802},
{"learn":[57.23693155],"iteration":61,"passed_time":0.07868849248,"remaining_time":1.190480741},
{"learn":[56.13019446],"iteration":62,"passed_time":0.07987248801,"remaining_time":1.187944782},
{"learn":[55.2676839],"iteration":63,"passed_time":0.08108799367,"remaining_time":1.185911907},
{"learn":[54.364003],"iteration":64,"passed_time":0.08231221133,"remaining_time":1.184029501},
{"learn":[53.47595158],"iteration":65,"passed_time":0.0836049238,"remaining_time":1.183136346},
{"learn":[52.56565662],"iteration":66,"passed_time":0.08487309136,"remaining_time":1.181889466},
{"learn":[51.61652433],"iteration":67,"passed_time":0.08608691135,"remaining_time":1.179897079},
{"learn":[50.87292316],"iteration":68,"passed_time":0.08723812498,"remaining_time":1.177082527},
{"learn":[50.03942725],"iteration":69,"passed_time":0.08849152174,"remaining_time":1.175673075},
{"learn":[49.33913694],"iteration":70,"passed_time":0.08965722867,"remaining_time":1.17312064},
{"learn":[48.43973927],"iteration":71,"passed_time":0.0909201049,"remaining_time":1.17185913},
{"learn":[47.55696394],"iteration":72,"passed_time":0.09214551861,"remaining_time":1.17012186},
{"learn":[46.84066642],"iteration":73,"passed_time":0.09340845805,"remaining_time":1.168868002},
{"learn":[46.18260915],"iteration":74,"passed_time":0.09457621566,"remaining_time":1.166439993},
{"learn":[45.39353952],"iteration":75,"passed_time":0.0957056904,"remaining_time":1.16357971},
{"learn":[44.56779653],"iteration":76,"passed_time":0.09690159393,"remaining_time":1.161560665},
{"learn":[43.840095],"iteration":77,"passed_time":0.09929874517,"remaining_time":1.17376209},
{"learn":[43.17062398],"iteration":78,"passed_time":0.1006087302,"remaining_time":1.1729195},
{"learn":[42.44819822],"iteration":79,"passed_time":0.1018534417,"remaining_time":1.17131458},
{"learn":[41.73632965],"iteration":80,"passed_time":0.1031544701,"remaining_time":1.170357507},
{"learn":[41.13464636],"iteration":81,"passed_time":0.1043188671,"remaining_time":1.167862439},
{"learn":[40.58664915],"iteration":82,"passed_time":0.1056308099,"remaining_time":1.167029551},
{"learn":[40.01582367],"iteration":83,"passed_time":0.1068890709,"remaining_time":1.165599868},
{"learn":[39.29741182],"iteration":84,"passed_time":0.1080997695,"remaining_time":1.163662225},
{"learn":[38.76461407],"iteration":85,"passed_time":0.1095176843,"remaining_time":1.163943761},
{"learn":[38.26521979],"iteration":86,"passed_time":0.1108846297,"remaining_time":1.163651344},
{"learn":[37.59083332],"iteration":87,"passed_time":0.1120370769,"remaining_time":1.161111524},
{"learn":[37.0044744],"iteration":88,"passed_time":0.113373875,"remaining_time":1.160489889},
{"learn":[36.37245945],"iteration":89,"passed_time":0.1146653522,"remaining_time":1.159394116},
{"learn":[35.87483809],"iteration":90,"passed_time":0.1159207749,"remaining_time":1.157933895},
{"learn":[35.40645552],"iteration":91,"passed_time":0.1171238348,"remaining_time":1.155961326},
{"learn":[34.76540411],"iteration":92,"passed_time":0.1183146434,"remaining_time":1.153885823},
{"learn":[34.23410717],"iteration":93,"passed_time":0.1196077859,"remaining_time":1.152815468},
{"learn":[33.80809676],"iteration":94,"passed_time":0.1209389458,"remaining_time":1.152102589},
{"learn":[33.43482795],"iteration":95,"passed_time":0.1220823778,"remaining_time":1.149609058},
{"learn":[32.89548366],"iteration":96,"passed_time":0.1232465666,"remaining_time":1.147336594},
{"learn":[32.45179956],"iteration":97,"passed_time":0.1245631608,"remaining_time":1.1464895},
{"learn":[32.08823898],"iteration":98,"passed_time":0.1258724665,"remaining_time":1.145566589},
{"learn":[31.64597578],"iteration":99,"passed_time":0.1270774938,"remaining_time":1.143697444},
{"learn":[31.21461589],"iteration":100,"passed_time":0.1283660474,"remaining_time":1.142584917},
{"learn":[30.87062315],"iteration":101,"passed_time":0.1297435651,"remaining_time":1.142252171},
{"learn":[30.58853826],"iteration":102,"passed_time":0.1309802454,"remaining_time":1.140672623},
{"learn":[30.2909123],"iteration":103,"passed_time":0.132220441,"remaining_time":1.139129953},
{"learn":[29.95308331],"iteration":104,"passed_time":0.133397472,"remaining_time":1.137054642},
{"learn":[29.61335526],"iteration":105,"passed_time":0.1345117295,"remaining_time":1.134466851},
{"learn":[29.14291717],"iteration":106,"passed_time":0.1356529347,"remaining_time":1.132131502},
{"learn":[28.73190461],"iteration":107,"passed_time":0.1368160435,"remaining_time":1.129999174},
{"learn":[28.33103051],"iteration":108,"passed_time":0.1380004937,"remaining_time":1.128059081},
{"learn":[28.02815092],"iteration":109,"passed_time":0.1392435499,"remaining_time":1.126606904},
{"learn":[27.5777749],"iteration":110,"passed_time":0.1408131705,"remaining_time":1.127773951},
{"learn":[27.29188557],"iteration":111,"passed_time":0.1421429491,"remaining_time":1.126990525},
{"learn":[27.03395932],"iteration":112,"passed_time":0.1432838483,"remaining_time":1.124714809},
{"learn":[26.73509903],"iteration":113,"passed_time":0.1444098663,"remaining_time":1.122343347},
{"learn":[26.38749961],"iteration":114,"passed_time":0.1455657699,"remaining_time":1.120223533},
{"learn":[26.05130677],"iteration":115,"passed_time":0.1467422994,"remaining_time":1.118277523},
{"learn":[25.79328408],"iteration":116,"passed_time":0.1480634157,"remaining_time":1.117435864},
{"learn":[25.56251924],"iteration":117,"passed_time":0.149252349,"remaining_time":1.115598066},
{"learn":[25.29397137],"iteration":118,"passed_time":0.1505250011,"remaining_time":1.114390975},
{"learn":[24.91652484],"iteration":119,"passed_time":0.1517487913,"remaining_time":1.112824469},
{"learn":[24.69115278],"iteration":120,"passed_time":0.1532174441,"remaining_time":1.113042424},
{"learn":[24.45534092],"iteration":121,"passed_time":0.1544119769,"remaining_time":1.111259965},
{"learn":[24.2139141],"iteration":122,"passed_time":0.1555921258,"remaining_time":1.109384506},
{"learn":[23.95375395],"iteration":123,"passed_time":0.1567979662,"remaining_time":1.107701761},
{"learn":[23.74924967],"iteration":124,"passed_time":0.1580480066,"remaining_time":1.106336046},
{"learn":[23.55053043],"iteration":125,"passed_time":0.1592019549,"remaining_time":1.104305623},
{"learn":[23.34535825],"iteration":126,"passed_time":0.1604403512,"remaining_time":1.102869501},
{"learn":[23.17389133],"iteration":127,"passed_time":0.161715889,"remaining_time":1.101689494},
{"learn":[22.90944827],"iteration":128,"passed_time":0.1629237094,"remaining_time":1.100050782},
{"learn":[22.7207743],"iteration":129,"passed_time":0.1641186994,"remaining_time":1.098332834},
{"learn":[22.49079055],"iteration":130,"passed_time":0.1653867173,"remaining_time":1.097107308},
{"learn":[22.26859984],"iteration":131,"passed_time":0.1667042554,"remaining_time":1.09620677},
{"learn":[22.15010402],"iteration":132,"passed_time":0.1678297474,"remaining_time":1.094048052},
{"learn":[21.95568048],"iteration":133,"passed_time":0.1689611971,"remaining_time":1.091943259},
{"learn":[21.69085512],"iteration":134,"passed_time":0.1714399368,"remaining_time":1.098485521},
{"learn":[21.47973046],"iteration":135,"passed_time":0.1727920946,"remaining_time":1.097738013},
{"learn":[21.27329928],"iteration":136,"passed_time":0.1740578826,"remaining_time":1.096437611},
{"learn":[21.0321017],"iteration":137,"passed_time":0.1753280833,"remaining_time":1.095165274},
{"learn":[20.86179699],"iteration":138,"passed_time":0.1767131505,"remaining_time":1.094604479},
{"learn":[20.67308289],"iteration":139,"passed_time":0.1781024138,"remaining_time":1.094057684},
{"learn":[20.48304847],"iteration":140,"passed_time":0.1794026386,"remaining_time":1.0929565},
{"learn":[20.33693434],"iteration":141,"passed_time":0.1806202253,"remaining_time":1.091353192},
{"learn":[20.11951195],"iteration":142,"passed_time":0.1820264653,"remaining_time":1.09088588},
{"learn":[19.90852937],"iteration":143,"passed_time":0.1833515122,"remaining_time":1.089922878},
{"learn":[19.71365813],"iteration":144,"passed_time":0.1846075771,"remaining_time":1.088548127},
{"learn":[19.56646064],"iteration":145,"passed_time":0.1859148083,"remaining_time":1.08747429},
{"learn":[19.40009097],"iteration":146,"passed_time":0.1873933752,"remaining_time":1.08739149},
{"learn":[19.29751691],"iteration":147,"passed_time":0.1886211935,"remaining_time":1.08584633},
{"learn":[19.18427131],"iteration":148,"passed_time":0.1898309125,"remaining_time":1.084202057},
{"learn":[19.06881893],"iteration":149,"passed_time":0.1909942727,"remaining_time":1.082300879},
{"learn":[18.88451474],"iteration":150,"passed_time":0.1922877112,"remaining_time":1.08114084},
{"learn":[18.66540702],"iteration":151,"passed_time":0.1935252608,"remaining_time":1.079667244},
{"learn":[18.49357392],"iteration":152,"passed_time":0.194731852,"remaining_time":1.07802535},
{"learn":[18.26296656],"iteration":153,"passed_time":0.1959073409,"remaining_time":1.076218249},
{"learn":[18.05319461],"iteration":154,"passed_time":0.1971627597,"remaining_time":1.074855045},
{"learn":[17.94024643],"iteration":155,"passed_time":0.1990562609,"remaining_time":1.076945411},
{"learn":[17.73632615],"iteration":156,"passed_time":0.2005879472,"remaining_time":1.07704229},
{"learn":[17.60205493],"iteration":157,"passed_time":0.2018951862,"remaining_time":1.075922448},
{"learn":[17.44495011],"iteration":158,"passed_time":0.203091694,"remaining_time":1.074214558},
{"learn":[17.31704363],"iteration":159,"passed_time":0.204336517,"remaining_time":1.072766714},
{"learn":[17.10569039],"iteration":160,"passed_time":0.2056610017,"remaining_time":1.071736525},
{"learn":[16.93532655],"iteration":161,"passed_time":0.2068639898,"remaining_time":1.070074219},
{"learn":[16.77222513],"iteration":162,"passed_time":0.208147491,"remaining_time":1.068830981},
{"learn":[16.59427462],"iteration":163,"passed_time":0.2093530176,"remaining_time":1.067189772},
{"learn":[16.4525718],"iteration":164,"passed_time":0.210542753,"remaining_time":1.065473932},
{"learn":[16.30319615],"iteration":165,"passed_time":0.2117702984,"remaining_time":1.063954391},
{"learn":[16.13281567],"iteration":166,"passed_time":0.2129895976,"remaining_time":1.062397214},
{"learn":[16.0036138],"iteration":167,"passed_time":0.2141704621,"remaining_time":1.060653717},
{"learn":[15.9189074],"iteration":168,"passed_time":0.2157119904,"remaining_time":1.06069032},
{"learn":[15.75331011],"iteration":169,"passed_time":0.2170269353,"remaining_time":1.059602096},
{"learn":[15.66021169],"iteration":170,"passed_time":0.2181976868,"remaining_time":1.057812178},
{"learn":[15.59326758],"iteration":171,"passed_time":0.2194399491,"remaining_time":1.056373709},
{"learn":[15.46411357],"iteration":172,"passed_time":0.2207530834,"remaining_time":1.0552763},
{"learn":[15.33748464],"iteration":173,"passed_time":0.2219584617,"remaining_time":1.053664882},
{"learn":[15.2633614],"iteration":174,"passed_time":0.2232325917,"remaining_time":1.052382218},
{"learn":[15.12118867],"iteration":175,"passed_time":0.2244101381,"remaining_time":1.050647465},
{"learn":[14.9220413],"iteration":176,"passed_time":0.2256350339,"remaining_time":1.049139169},
{"learn":[14.82550128],"iteration":177,"passed_time":0.2269939334,"remaining_time":1.048252883},
{"learn":[14.70932674],"iteration":178,"passed_time":0.2282807667,"remaining_time":1.047030779},
{"learn":[14.64979102],"iteration":179,"passed_time":0.2295357534,"remaining_time":1.045662877},
{"learn":[14.55646726],"iteration":180,"passed_time":0.230703621,"remaining_time":1.04390202},
{"learn":[14.45093082],"iteration":181,"passed_time":0.2320076701,"remaining_time":1.042759748},
{"learn":[14.34909777],"iteration":182,"passed_time":0.2331850714,"remaining_time":1.041050292},
{"learn":[14.22569635],"iteration":183,"passed_time":0.2343808728,"remaining_time":1.039428219},
{"learn":[14.17665722],"iteration":184,"passed_time":0.2356995538,"remaining_time":1.038352088},
{"learn":[14.072916],"iteration":185,"passed_time":0.2368651689,"remaining_time":1.036603481},
{"learn":[13.99681841],"iteration":186,"passed_time":0.2380774468,"remaining_time":1.03506398},
{"learn":[13.89505646],"iteration":187,"passed_time":0.2392374352,"remaining_time":1.033302114},
{"learn":[13.77430888],"iteration":188,"passed_time":0.2403828665,"remaining_time":1.031484152},
{"learn":[13.68874144],"iteration":189,"passed_time":0.2417442177,"remaining_time":1.03059377},
{"learn":[13.5630002],"iteration":190,"passed_time":0.2430659386,"remaining_time":1.029530598},
{"learn":[13.4511696],"iteration":191,"passed_time":0.2442269617,"remaining_time":1.027788464},
{"learn":[13.31719998],"iteration":192,"passed_time":0.2454525,"remaining_time":1.026322111},
{"learn":[13.23469074],"iteration":193,"passed_time":0.2466943348,"remaining_time":1.024925948},
{"learn":[13.11848073],"iteration":194,"passed_time":0.2479479416,"remaining_time":1.023579964},
{"learn":[13.02261723],"iteration":195,"passed_time":0.2491809559,"remaining_time":1.022150452},
{"learn":[12.9643116],"iteration":196,"passed_time":0.2505955133,"remaining_time":1.02146293},
{"learn":[12.86680156],"iteration":197,"passed_time":0.2518886775,"remaining_time":1.02027636},
{"learn":[12.77511641],"iteration":198,"passed_time":0.2531475027,"remaining_time":1.018950501},
{"learn":[12.71135528],"iteration":199,"passed_time":0.2545998177,"remaining_time":1.018399271},
{"learn":[12.55111259],"iteration":200,"passed_time":0.255804581,"remaining_time":1.016855026},
{"learn":[12.45329237],"iteration":201,"passed_time":0.2569635545,"remaining_time":1.01513325},
{"learn":[12.37252596],"iteration":202,"passed_time":0.2581468854,"remaining_time":1.013512649},
{"learn":[12.3069833],"iteration":203,"passed_time":0.2596172182,"remaining_time":1.013016204},
{"learn":[12.24112279],"iteration":204,"passed_time":0.2607950471,"remaining_time":1.011375914},
{"learn":[12.13420908],"iteration":205,"passed_time":0.2621856774,"remaining_time":1.010560329},
{"learn":[12.03476036],"iteration":206,"passed_time":0.2635984309,"remaining_time":1.009823941},
{"learn":[11.92115826],"iteration":207,"passed_time":0.2648652303,"remaining_time":1.0085253},
{"learn":[11.83603708],"iteration":208,"passed_time":0.2660535782,"remaining_time":1.00693005},
{"learn":[11.72609027],"iteration":209,"passed_time":0.2674853706,"remaining_time":1.00625449},
{"learn":[11.66443338],"iteration":210,"passed_time":0.268680526,"remaining_time":1.004686896},
{"learn":[11.54888554],"iteration":211,"passed_time":0.2698884925,"remaining_time":1.003170434},
{"learn":[11.5137156],"iteration":212,"passed_time":0.2712023999,"remaining_time":1.002048304},
{"learn":[11.4403413],"iteration":213,"passed_time":0.2725109868,"remaining_time":1.000904839},
{"learn":[11.37794315],"iteration":214,"passed_time":0.2737292577,"remaining_time":0.9994300806},
{"learn":[11.33634124],"iteration":215,"passed_time":0.2749494687,"remaining_time":0.9979647382},
{"learn":[11.28704622],"iteration":216,"passed_time":0.2761173409,"remaining_time":0.9963128016},
{"learn":[11.16991652],"iteration":217,"passed_time":0.2773505313,"remaining_time":0.9948996122},
{"learn":[11.04240168],"iteration":218,"passed_time":0.2786644934,"remaining_time":0.9937761156},
{"learn":[11.01163933],"iteration":219,"passed_time":0.2799052789,"remaining_time":0.9923914435},
{"learn":[10.9216878],"iteration":220,"passed_time":0.2813352953,"remaining_time":0.9916750907},
{"learn":[10.83476677],"iteration":221,"passed_time":0.2824979816,"remaining_time":0.990015449},
{"learn":[10.74802808],"iteration":222,"passed_time":0.2836717837,"remaining_time":0.9883989954},
{"learn":[10.69084672],"iteration":223,"passed_time":0.28514942,"remaining_time":0.9878390621},
{"learn":[10.61171196],"iteration":224,"passed_time":0.2863753283,"remaining_time":0.9864039086},
{"learn":[10.56185547],"iteration":225,"passed_time":0.2876374549,"remaining_time":0.9850946465},
{"learn":[10.48599855],"iteration":226,"passed_time":0.2903563153,"remaining_time":0.9887463952},
{"learn":[10.42212695],"iteration":227,"passed_time":0.2915708803,"remaining_time":0.98724877},
{"learn":[10.38935905],"iteration":228,"passed_time":0.2927688809,"remaining_time":0.9856978479},
{"learn":[10.33976163],"iteration":229,"passed_time":0.2939814213,"remaining_time":0.9841986711},
{"learn":[10.30733411],"iteration":230,"passed_time":0.2954347176,"remaining_time":0.9835034538},
{"learn":[10.21707618],"iteration":231,"passed_time":0.2969640247,"remaining_time":0.983053323},
{"learn":[10.19155911],"iteration":232,"passed_time":0.2981484409,"remaining_time":0.9814586016},
{"learn":[10.10796478],"iteration":233,"passed_time":0.2993820173,"remaining_time":0.9800283131},
{"learn":[10.03790262],"iteration":234,"passed_time":0.3006082581,"remaining_time":0.978575819},
{"learn":[9.97481783],"iteration":235,"passed_time":0.301834785,"remaining_time":0.9771261685},
{"learn":[9.889224722],"iteration":236,"passed_time":0.303279989,"remaining_time":0.9763824119},
{"learn":[9.823409388],"iteration":237,"passed_time":0.3046581081,"remaining_time":0.9754179765},
{"learn":[9.794186883],"iteration":238,"passed_time":0.3058451629,"remaining_time":0.9738417111},
{"learn":[9.765607808],"iteration":239,"passed_time":0.3072637588,"remaining_time":0.9730019028},
{"learn":[9.712204001],"iteration":240,"passed_time":0.3086003237,"remaining_time":0.9718989447},
{"learn":[9.643013725],"iteration":241,"passed_time":0.3099626063,"remaining_time":0.9708746098},
{"learn":[9.619990612],"iteration":242,"passed_time":0.3111753302,"remaining_time":0.9693815843},
{"learn":[9.554216283],"iteration":243,"passed_time":0.3126414699,"remaining_time":0.9686760297},
{"learn":[9.478221157],"iteration":244,"passed_time":0.3138913346,"remaining_time":0.9672977862},
{"learn":[9.406205076],"iteration":245,"passed_time":0.3151677199,"remaining_time":0.966001873},
{"learn":[9.340623943],"iteration":246,"passed_time":0.3166091357,"remaining_time":0.9652092274},
{"learn":[9.265861527],"iteration":247,"passed_time":0.3179884241,"remaining_time":0.9642229633},
{"learn":[9.246351746],"iteration":248,"passed_time":0.3191859594,"remaining_time":0.9626853634},
{"learn":[9.171485141],"iteration":249,"passed_time":0.3204590547,"remaining_time":0.9613771641},
{"learn":[9.102409766],"iteration":250,"passed_time":0.32165373,"remaining_time":0.9598352342},
{"learn":[9.03495858],"iteration":251,"passed_time":0.3230627432,"remaining_time":0.9589322696},
{"learn":[9.000421388],"iteration":252,"passed_time":0.324314194,"remaining_time":0.9575600905},
{"learn":[8.931265295],"iteration":253,"passed_time":0.3256931284,"remaining_time":0.9565632827},
{"learn":[8.871159479],"iteration":254,"passed_time":0.3269559632,"remaining_time":0.9552242847},
{"learn":[8.77718165],"iteration":255,"passed_time":0.3283382055,"remaining_time":0.9542329097},
{"learn":[8.746711532],"iteration":256,"passed_time":0.3295293809,"remaining_time":0.952686109},
{"learn":[8.669513045],"iteration":257,"passed_time":0.3307155689,"remaining_time":0.9511277214},
{"learn":[8.640073124],"iteration":258,"passed_time":0.3318737792,"remaining_time":0.9494921636},
{"learn":[8.621346684],"iteration":259,"passed_time":0.3326555995,"remaining_time":0.9467890141},
{"learn":[8.545494574],"iteration":260,"passed_time":0.333856698,"remaining_time":0.9452877387},
{"learn":[8.461005835],"iteration":261,"passed_time":0.3349949822,"remaining_time":0.9436118201},
{"learn":[8.398355104],"iteration":262,"passed_time":0.3364025911,"remaining_time":0.9426947136},
{"learn":[8.344420748],"iteration":263,"passed_time":0.3375597961,"remaining_time":0.9410757952},
{"learn":[8.28293522],"iteration":264,"passed_time":0.3389935946,"remaining_time":0.940227517},
{"learn":[8.223327014],"iteration":265,"passed_time":0.3403133833,"remaining_time":0.9390602382},
{"learn":[8.186006215],"iteration":266,"passed_time":0.3414927547,"remaining_time":0.9375063264},
{"learn":[8.138690412],"iteration":267,"passed_time":0.3429042775,"remaining_time":0.9365892951},
{"learn":[8.093093637],"iteration":268,"passed_time":0.3442813498,"remaining_time":0.9355749692},
{"learn":[8.018117163],"iteration":269,"passed_time":0.3455254482,"remaining_time":0.934198434},
{"learn":[7.972501556],"iteration":270,"passed_time":0.3466731469,"remaining_time":0.9325635574},
{"learn":[7.912258945],"iteration":271,"passed_time":0.3478310857,"remaining_time":0.9309596706},
{"learn":[7.841322138],"iteration":272,"passed_time":0.3492718216,"remaining_time":0.9301121402},
{"learn":[7.785789978],"iteration":273,"passed_time":0.3505946064,"remaining_time":0.9289477526},
{"learn":[7.734152963],"iteration":274,"passed_time":0.3518513898,"remaining_time":0.9276082096},
{"learn":[7.668306982],"iteration":275,"passed_time":0.3531259451,"remaining_time":0.9263158851},
{"learn":[7.632597072],"iteration":276,"passed_time":0.3543217976,"remaining_time":0.9248182659},
{"learn":[7.579170618],"iteration":277,"passed_time":0.3554866878,"remaining_time":0.9232424049},
{"learn":[7.511619416],"iteration":278,"passed_time":0.356887995,"remaining_time":0.922280446},
{"learn":[7.460910868],"iteration":279,"passed_time":0.3581484763,"remaining_time":0.9209532248},
{"learn":[7.41558184],"iteration":280,"passed_time":0.3593851841,"remaining_time":0.919565649},
{"learn":[7.359261624],"iteration":281,"passed_time":0.3605522978,"remaining_time":0.9180019497},
{"learn":[7.289788557],"iteration":282,"passed_time":0.3617558219,"remaining_time":0.9165333014},
{"learn":[7.26245707],"iteration":283,"passed_time":0.3637605442,"remaining_time":0.9170864425},
{"learn":[7.219429515],"iteration":284,"passed_time":0.3650642858,"remaining_time":0.9158630328},
{"learn":[7.151285214],"iteration":285,"passed_time":0.3663224139,"remaining_time":0.9145251871},
{"learn":[7.075846515],"iteration":286,"passed_time":0.3674653462,"remaining_time":0.9129017138},
{"learn":[7.007659644],"iteration":287,"passed_time":0.3686695328,"remaining_time":0.9114330117},
{"learn":[6.950434279],"iteration":288,"passed_time":0.3698628435,"remaining_time":0.9099393832},
{"learn":[6.926439095],"iteration":289,"passed_time":0.3710316897,"remaining_time":0.90838793},
{"learn":[6.851636547],"iteration":290,"passed_time":0.3722163802,"remaining_time":0.9068777099},
{"learn":[6.793370565],"iteration":291,"passed_time":0.3733901524,"remaining_time":0.9053432461},
{"learn":[6.740340209],"iteration":292,"passed_time":0.3747895847,"remaining_time":0.9043557555},
{"learn":[6.684234572],"iteration":293,"passed_time":0.3760155098,"remaining_time":0.9029488092},
{"learn":[6.628367885],"iteration":294,"passed_time":0.3774571863,"remaining_time":0.9020586996},
{"learn":[6.580309088],"iteration":295,"passed_time":0.3787859224,"remaining_time":0.900896248},
{"learn":[6.532172984],"iteration":296,"passed_time":0.3800056316,"remaining_time":0.8994746095},
{"learn":[6.521422561],"iteration":297,"passed_time":0.3811732878,"remaining_time":0.8979317048},
{"learn":[6.515218694],"iteration":298,"passed_time":0.3823382769,"remaining_time":0.8963850572},
{"learn":[6.46287245],"iteration":299,"passed_time":0.3835952664,"remaining_time":0.8950556217},
{"learn":[6.40813036],"iteration":300,"passed_time":0.3848135178,"remaining_time":0.8936367074},
{"learn":[6.352974796],"iteration":301,"passed_time":0.3862842627,"remaining_time":0.8928026999},
{"learn":[6.300351871],"iteration":302,"passed_time":0.387506674,"remaining_time":0.8913932401},
{"learn":[6.25092819],"iteration":303,"passed_time":0.3887470135,"remaining_time":0.8900260571},
{"learn":[6.19831791],"iteration":304,"passed_time":0.3900117714,"remaining_time":0.888715348},
{"learn":[6.181983706],"iteration":305,"passed_time":0.3912929641,"remaining_time":0.8874422127},
{"learn":[6.134576059],"iteration":306,"passed_time":0.3924802128,"remaining_time":0.8859569625},
{"learn":[6.085798888],"iteration":307,"passed_time":0.3937530221,"remaining_time":0.8846658808},
{"learn":[6.069739891],"iteration":308,"passed_time":0.3952683819,"remaining_time":0.8839173201},
{"learn":[6.021670788],"iteration":309,"passed_time":0.396536898,"remaining_time":0.882614386},
{"learn":[5.97639725],"iteration":310,"passed_time":0.3978088495,"remaining_time":0.8813192839},
{"learn":[5.920637979],"iteration":311,"passed_time":0.3989542586,"remaining_time":0.8797452881},
{"learn":[5.872064495],"iteration":312,"passed_time":0.4001898089,"remaining_time":0.8783718808},
{"learn":[5.829630408],"iteration":313,"passed_time":0.4013639238,"remaining_time":0.876865133},
{"learn":[5.786117118],"iteration":314,"passed_time":0.4025350721,"remaining_time":0.8753540457},
{"learn":[5.742670505],"iteration":315,"passed_time":0.403870341,"remaining_time":0.8742003583},
{"learn":[5.728388254],"iteration":316,"passed_time":0.4050685541,"remaining_time":0.8727502285},
{"learn":[5.688290429],"iteration":317,"passed_time":0.4062985045,"remaining_time":0.8713697486},
{"learn":[5.634988965],"iteration":318,"passed_time":0.4076221053,"remaining_time":0.8701901371},
{"learn":[5.593886135],"iteration":319,"passed_time":0.4088010895,"remaining_time":0.8687023152},
{"learn":[5.54787875],"iteration":320,"passed_time":0.4099609537,"remaining_time":0.8671759737},
{"learn":[5.497341733],"iteration":321,"passed_time":0.4111162158,"remaining_time":0.8656422184},
{"learn":[5.454439432],"iteration":322,"passed_time":0.4123333482,"remaining_time":0.8642404853},
{"learn":[5.407952738],"iteration":323,"passed_time":0.4135021158,"remaining_time":0.8627389824},
{"learn":[5.356588232],"iteration":324,"passed_time":0.414753508,"remaining_time":0.861411132},
{"learn":[5.314064192],"iteration":325,"passed_time":0.4159226863,"remaining_time":0.8599137747},
{"learn":[5.262588969],"iteration":326,"passed_time":0.4170698454,"remaining_time":0.8583731068},
{"learn":[5.229180115],"iteration":327,"passed_time":0.4184667324,"remaining_time":0.857346476},
{"learn":[5.184767988],"iteration":328,"passed_time":0.419909045,"remaining_time":0.8564102406},
{"learn":[5.177069526],"iteration":329,"passed_time":0.4210803171,"remaining_time":0.8549206439},
{"learn":[5.14618705],"iteration":330,"passed_time":0.4223822802,"remaining_time":0.8536971161},
{"learn":[5.103426888],"iteration":331,"passed_time":0.4236634414,"remaining_time":0.8524312616},
{"learn":[5.071603476],"iteration":332,"passed_time":0.4249748203,"remaining_time":0.8512258413},
{"learn":[5.034233294],"iteration":333,"passed_time":0.4263196658,"remaining_time":0.8500865192},
{"learn":[5.000244029],"iteration":334,"passed_time":0.4274779529,"remaining_time":0.8485756378},
{"learn":[4.988431759],"iteration":335,"passed_time":0.4286366856,"remaining_time":0.8470677359},
{"learn":[4.937626059],"iteration":336,"passed_time":0.429909521,"remaining_time":0.8457863869},
{"learn":[4.888077991],"iteration":337,"passed_time":0.4310716819,"remaining_time":0.8442883237},
{"learn":[4.876733148],"iteration":338,"passed_time":0.4323074247,"remaining_time":0.842935716},
{"learn":[4.847169437],"iteration":339,"passed_time":0.4335314738,"remaining_time":0.8415610962},
{"learn":[4.809448232],"iteration":340,"passed_time":0.4361777887,"remaining_time":0.8429359611},
{"learn":[4.779669091],"iteration":341,"passed_time":0.4376449062,"remaining_time":0.8420185622},
{"learn":[4.7403607],"iteration":342,"passed_time":0.4388358534,"remaining_time":0.840568967},
{"learn":[4.704431007],"iteration":343,"passed_time":0.4401797828,"remaining_time":0.839412609},
{"learn":[4.659207936],"iteration":344,"passed_time":0.4414319688,"remaining_time":0.8380809843},
{"learn":[4.6257518],"iteration":345,"passed_time":0.4426058863,"remaining_time":0.8366018776},
{"learn":[4.590764128],"iteration":346,"passed_time":0.4437926618,"remaining_time":0.8351487267},
{"learn":[4.55651005],"iteration":347,"passed_time":0.4450820126,"remaining_time":0.8338892879},
{"learn":[4.523305649],"iteration":348,"passed_time":0.4463901898,"remaining_time":0.8326647952},
{"learn":[4.517752254],"iteration":349,"passed_time":0.4476091811,"remaining_time":0.8312741934},
{"learn":[4.480418115],"iteration":350,"passed_time":0.4487675096,"remaining_time":0.8297724037},
{"learn":[4.473701226],"iteration":351,"passed_time":0.4499795914,"remaining_time":0.8283715205},
{"learn":[4.443217537],"iteration":352,"passed_time":0.4512013705,"remaining_time":0.8269894808},
{"learn":[4.410294126],"iteration":353,"passed_time":0.4523354869,"remaining_time":0.8254483745},
{"learn":[4.400476883],"iteration":354,"passed_time":0.4535117612,"remaining_time":0.8239861576},
{"learn":[4.373151473],"iteration":355,"passed_time":0.4546863772,"remaining_time":0.8225225476},
{"learn":[4.333617542],"iteration":356,"passed_time":0.4558647914,"remaining_time":0.8210673975},
{"learn":[4.306843373],"iteration":357,"passed_time":0.4571187743,"remaining_time":0.8197493103},
{"learn":[4.304282455],"iteration":358,"passed_time":0.4584442386,"remaining_time":0.8185592116},
{"learn":[4.302014527],"iteration":359,"passed_time":0.4596567611,"remaining_time":0.8171675754},
{"learn":[4.290107184],"iteration":360,"passed_time":0.4608271641,"remaining_time":0.8157023763},
{"learn":[4.276168991],"iteration":361,"passed_time":0.4621005219,"remaining_time":0.8144202568},
{"learn":[4.273782161],"iteration":362,"passed_time":0.4633508469,"remaining_time":0.8130977672},
{"learn":[4.259906366],"iteration":363,"passed_time":0.4647480807,"remaining_time":0.8120323608},
{"learn":[4.25175802],"iteration":364,"passed_time":0.4659588593,"remaining_time":0.8106407553},
{"learn":[4.247072735],"iteration":365,"passed_time":0.4671578164,"remaining_time":0.80922966},
{"learn":[4.240870124],"iteration":366,"passed_time":0.4683904596,"remaining_time":0.8078778226},
{"learn":[4.220673708],"iteration":367,"passed_time":0.4697169104,"remaining_time":0.8066877374},
{"learn":[4.191466688],"iteration":368,"passed_time":0.4709379795,"remaining_time":0.8053167075},
{"learn":[4.189515484],"iteration":369,"passed_time":0.4721179483,"remaining_time":0.8038765066},
{"learn":[4.161258852],"iteration":370,"passed_time":0.4734001317,"remaining_time":0.8026110049},
{"learn":[4.14666845],"iteration":371,"passed_time":0.4746023669,"remaining_time":0.8012104473},
{"learn":[4.115288454],"iteration":372,"passed_time":0.4757800911,"remaining_time":0.799769751},
{"learn":[4.109522337],"iteration":373,"passed_time":0.4769592946,"remaining_time":0.7983329369},
{"learn":[4.079720186],"iteration":374,"passed_time":0.478179813,"remaining_time":0.796966355},
{"learn":[4.075763264],"iteration":375,"passed_time":0.4794521209,"remaining_time":0.7956864984},
{"learn":[4.042116584],"iteration":376,"passed_time":0.4806410263,"remaining_time":0.7942688578},
{"learn":[4.010586445],"iteration":377,"passed_time":0.4818207883,"remaining_time":0.7928373819},
{"learn":[3.987294504],"iteration":378,"passed_time":0.483097195,"remaining_time":0.7915655887},
{"learn":[3.953489218],"iteration":379,"passed_time":0.4843602366,"remaining_time":0.790271965},
{"learn":[3.929925017],"iteration":380,"passed_time":0.4855495674,"remaining_time":0.788858746},
{"learn":[3.90490496],"iteration":381,"passed_time":0.4866972536,"remaining_time":0.7873793265},
{"learn":[3.876971872],"iteration":382,"passed_time":0.4878566978,"remaining_time":0.785920581},
{"learn":[3.859643837],"iteration":383,"passed_time":0.4890304321,"remaining_time":0.7844863181},
{"learn":[3.83127105],"iteration":384,"passed_time":0.4902489873,"remaining_time":0.7831250057},
{"learn":[3.805019275],"iteration":385,"passed_time":0.4915143349,"remaining_time":0.7818388644},
{"learn":[3.784771831],"iteration":386,"passed_time":0.4927152537,"remaining_time":0.7804507766},
{"learn":[3.777826391],"iteration":387,"passed_time":0.4940069862,"remaining_time":0.7792068958},
{"learn":[3.75926347],"iteration":388,"passed_time":0.4952952688,"remaining_time":0.7779573502},
{"learn":[3.734740016],"iteration":389,"passed_time":0.4964459131,"remaining_time":0.7764923257},
{"learn":[3.72367061],"iteration":390,"passed_time":0.497775171,"remaining_time":0.7753071078},
{"learn":[3.698653786],"iteration":391,"passed_time":0.4991304109,"remaining_time":0.7741614537},
{"learn":[3.673217924],"iteration":392,"passed_time":0.5002929118,"remaining_time":0.7727170419},
{"learn":[3.664041318],"iteration":393,"passed_time":0.5015071418,"remaining_time":0.7713536242},
{"learn":[3.650438657],"iteration":394,"passed_time":0.5028314341,"remaining_time":0.7701595383},
{"learn":[3.631924624],"iteration":395,"passed_time":0.5040400584,"remaining_time":0.768788372},
{"learn":[3.626345512],"iteration":396,"passed_time":0.5052786426,"remaining_time":0.7674635302},
{"learn":[3.609536083],"iteration":397,"passed_time":0.5064723487,"remaining_time":0.766071241},
{"learn":[3.584292527],"iteration":398,"passed_time":0.5077354867,"remaining_time":0.7647845301},
{"learn":[3.561516222],"iteration":399,"passed_time":0.5088749698,"remaining_time":0.7633124547},
{"learn":[3.553859695],"iteration":400,"passed_time":0.5100502305,"remaining_time":0.7618954815},
{"learn":[3.537367945],"iteration":401,"passed_time":0.5113747674,"remaining_time":0.7607017684},
{"learn":[3.510667098],"iteration":402,"passed_time":0.5127395525,"remaining_time":0.7595670294},
{"learn":[3.503411707],"iteration":403,"passed_time":0.5138499311,"remaining_time":0.758055839},
{"learn":[3.49608052],"iteration":404,"passed_time":0.5150162981,"remaining_time":0.7566288823},
{"learn":[3.475471604],"iteration":405,"passed_time":0.516246197,"remaining_time":0.7552961602},
{"learn":[3.449198477],"iteration":406,"passed_time":0.5173545979,"remaining_time":0.7537869203},
{"learn":[3.423930422],"iteration":407,"passed_time":0.518611236,"remaining_time":0.7524947346},
{"learn":[3.405580953],"iteration":408,"passed_time":0.5198698534,"remaining_time":0.7512055828},
{"learn":[3.387260098],"iteration":409,"passed_time":0.5210708008,"remaining_time":0.7498335913},
{"learn":[3.378609215],"iteration":410,"passed_time":0.5222708581,"remaining_time":0.7484611568},
{"learn":[3.35378336],"iteration":411,"passed_time":0.5234762808,"remaining_time":0.7470972162},
{"learn":[3.329008946],"iteration":412,"passed_time":0.5246880886,"remaining_time":0.7457431187},
{"learn":[3.305787014],"iteration":413,"passed_time":0.52588409,"remaining_time":0.7443673352},
{"learn":[3.282622298],"iteration":414,"passed_time":0.5270799407,"remaining_time":0.7429922056},
{"learn":[3.26350572],"iteration":415,"passed_time":0.5282525757,"remaining_time":0.7415853467},
{"learn":[3.241002604],"iteration":416,"passed_time":0.5294104046,"remaining_time":0.740158911},
{"learn":[3.223306666],"iteration":417,"passed_time":0.5308756682,"remaining_time":0.7391618155},
{"learn":[3.20086445],"iteration":418,"passed_time":0.5320501382,"remaining_time":0.7377592608},
{"learn":[3.18981728],"iteration":419,"passed_time":0.5331842475,"remaining_time":0.736302056},
{"learn":[3.169683366],"iteration":420,"passed_time":0.5344252723,"remaining_time":0.7349934268},
{"learn":[3.155081176],"iteration":421,"passed_time":0.5357032761,"remaining_time":0.7337357668},
{"learn":[3.130266257],"iteration":422,"passed_time":0.5369198961,"remaining_time":0.732394279},
{"learn":[3.110442513],"iteration":423,"passed_time":0.5380404281,"remaining_time":0.7309228457},
{"learn":[3.089413577],"iteration":424,"passed_time":0.53916881,"remaining_time":0.7294636841},
{"learn":[3.086210574],"iteration":425,"passed_time":0.5395904877,"remaining_time":0.7270538496},
{"learn":[3.083186951],"iteration":426,"passed_time":0.5399533018,"remaining_time":0.724574337},
{"learn":[3.059554098],"iteration":427,"passed_time":0.5410731885,"remaining_time":0.7231165042},
{"learn":[3.040078679],"iteration":428,"passed_time":0.5422009582,"remaining_time":0.7216707393},
{"learn":[3.023410721],"iteration":429,"passed_time":0.5433545133,"remaining_time":0.7202606338},
{"learn":[3.003987227],"iteration":430,"passed_time":0.5446217965,"remaining_time":0.7190018613},
{"learn":[2.9808016],"iteration":431,"passed_time":0.5458458563,"remaining_time":0.7176862185},
{"learn":[2.964193837],"iteration":432,"passed_time":0.5470345511,"remaining_time":0.7163246893},
{"learn":[2.951071507],"iteration":433,"passed_time":0.5482404508,"remaining_time":0.7149863944},
{"learn":[2.933427788],"iteration":434,"passed_time":0.549641847,"remaining_time":0.7139026289},
{"learn":[2.916232644],"iteration":435,"passed_time":0.5521149144,"remaining_time":0.7142036966},
{"learn":[2.894996831],"iteration":436,"passed_time":0.5533054098,"remaining_time":0.7128396927},
{"learn":[2.888382648],"iteration":437,"passed_time":0.553864595,"remaining_time":0.7106664438},
{"learn":[2.86601343],"iteration":438,"passed_time":0.5550434692,"remaining_time":0.7092924515},
{"learn":[2.852166159],"iteration":439,"passed_time":0.5563278236,"remaining_time":0.7080535936},
{"learn":[2.845941974],"iteration":440,"passed_time":0.5574503495,"remaining_time":0.7066093999},
{"learn":[2.833910346],"iteration":441,"passed_time":0.5583798933,"remaining_time":0.7049230327},
{"learn":[2.820109796],"iteration":442,"passed_time":0.5596195174,"remaining_time":0.7036299576},
{"learn":[2.800342335],"iteration":443,"passed_time":0.5609221786,"remaining_time":0.7024160615},
{"learn":[2.781681155],"iteration":444,"passed_time":0.5623210663,"remaining_time":0.7013217793},
{"learn":[2.779126805],"iteration":445,"passed_time":0.562829457,"remaining_time":0.6991199982},
{"learn":[2.770767095],"iteration":446,"passed_time":0.5640878869,"remaining_time":0.6978536945},
{"learn":[2.751264727],"iteration":447,"passed_time":0.5652337946,"remaining_time":0.6964487826},
{"learn":[2.739268342],"iteration":448,"passed_time":0.5664173747,"remaining_time":0.695091255},
{"learn":[2.727251884],"iteration":449,"passed_time":0.5677196299,"remaining_time":0.6938795477},
{"learn":[2.715802747],"iteration":450,"passed_time":0.5690018172,"remaining_time":0.6926430103},
{"learn":[2.69043446],"iteration":451,"passed_time":0.5702015032,"remaining_time":0.6913062472},
{"learn":[2.672467839],"iteration":452,"passed_time":0.5714028909,"remaining_time":0.6899721442},
{"learn":[2.659959677],"iteration":453,"passed_time":0.5726241861,"remaining_time":0.6886625674},
{"learn":[2.644883332],"iteration":454,"passed_time":0.573865177,"remaining_time":0.6873769702},
{"learn":[2.632854636],"iteration":455,"passed_time":0.5751134478,"remaining_time":0.6861002535},
{"learn":[2.625305185],"iteration":456,"passed_time":0.5763991843,"remaining_time":0.6848681774},
{"learn":[2.622988561],"iteration":457,"passed_time":0.5768341332,"remaining_time":0.6826290397},
{"learn":[2.608503827],"iteration":458,"passed_time":0.5779991401,"remaining_time":0.6812582457},
{"learn":[2.594743654],"iteration":459,"passed_time":0.5791218782,"remaining_time":0.6798387266},
{"learn":[2.578647174],"iteration":460,"passed_time":0.5803193688,"remaining_time":0.6785078954},
{"learn":[2.566832401],"iteration":461,"passed_time":0.5815268814,"remaining_time":0.6771893121},
{"learn":[2.551067266],"iteration":462,"passed_time":0.5828489637,"remaining_time":0.6760040897},
{"learn":[2.531317789],"iteration":463,"passed_time":0.5840986498,"remaining_time":0.6747346472},
{"learn":[2.516774556],"iteration":464,"passed_time":0.5852653489,"remaining_time":0.67336981},
{"learn":[2.507453317],"iteration":465,"passed_time":0.5864124379,"remaining_time":0.6719833516},
{"learn":[2.493087622],"iteration":466,"passed_time":0.5876909653,"remaining_time":0.6707479326},
{"learn":[2.477080948],"iteration":467,"passed_time":0.5888317491,"remaining_time":0.669355749},
{"learn":[2.469205669],"iteration":468,"passed_time":0.5895924456,"remaining_time":0.6675343041},
{"learn":[2.451998803],"iteration":469,"passed_time":0.5907360329,"remaining_time":0.6661491435},
{"learn":[2.437545169],"iteration":470,"passed_time":0.5918606413,"remaining_time":0.6647436927},
{"learn":[2.424153895],"iteration":471,"passed_time":0.5930257619,"remaining_time":0.6633847506},
{"learn":[2.411292605],"iteration":472,"passed_time":0.5941610265,"remaining_time":0.6619933636},
{"learn":[2.39812934],"iteration":473,"passed_time":0.5954091634,"remaining_time":0.6607283121},
{"learn":[2.383804806],"iteration":474,"passed_time":0.5966226658,"remaining_time":0.6594250517},
{"learn":[2.36985938],"iteration":475,"passed_time":0.5977932713,"remaining_time":0.6580749457},
{"learn":[2.352421955],"iteration":476,"passed_time":0.5989395818,"remaining_time":0.6566989544},
{"learn":[2.34278287],"iteration":477,"passed_time":0.600102538,"remaining_time":0.6553421022},
{"learn":[2.333753691],"iteration":478,"passed_time":0.6012625286,"remaining_time":0.6539828339},
{"learn":[2.320947371],"iteration":479,"passed_time":0.6024098298,"remaining_time":0.652610649},
{"learn":[2.315608517],"iteration":480,"passed_time":0.6035352572,"remaining_time":0.6512157972},
{"learn":[2.308311979],"iteration":481,"passed_time":0.6046496686,"remaining_time":0.6498102248},
{"learn":[2.294996405],"iteration":482,"passed_time":0.6060719234,"remaining_time":0.6487353714},
{"learn":[2.279336513],"iteration":483,"passed_time":0.6072650959,"remaining_time":0.6474148543},
{"learn":[2.26752118],"iteration":484,"passed_time":0.6084355281,"remaining_time":0.6460707154},
{"learn":[2.251330569],"iteration":485,"passed_time":0.6095571883,"remaining_time":0.6446757094},
{"learn":[2.237496368],"iteration":486,"passed_time":0.6106866384,"remaining_time":0.6432900318},
{"learn":[2.230715752],"iteration":487,"passed_time":0.6119894021,"remaining_time":0.6420872416},
{"learn":[2.218246336],"iteration":488,"passed_time":0.6133012457,"remaining_time":0.6408935307},
{"learn":[2.209107603],"iteration":489,"passed_time":0.6145451133,"remaining_time":0.6396285873},
{"learn":[2.195043704],"iteration":490,"passed_time":0.6157685631,"remaining_time":0.6383425634},
{"learn":[2.178909819],"iteration":491,"passed_time":0.616917805,"remaining_time":0.6369801726},
{"learn":[2.167656754],"iteration":492,"passed_time":0.6181703025,"remaining_time":0.6357248344},
{"learn":[2.153457362],"iteration":493,"passed_time":0.6193356448,"remaining_time":0.6343802354},
{"learn":[2.143370629],"iteration":494,"passed_time":0.6204801628,"remaining_time":0.6330151156},
{"learn":[2.132694052],"iteration":495,"passed_time":0.6216189478,"remaining_time":0.6316450598},
{"learn":[2.123757078],"iteration":496,"passed_time":0.6228103671,"remaining_time":0.6303292045},
{"learn":[2.117657781],"iteration":497,"passed_time":0.6240093477,"remaining_time":0.629021471},
{"learn":[2.104172014],"iteration":498,"passed_time":0.625333186,"remaining_time":0.6278395315},
{"learn":[2.097627938],"iteration":499,"passed_time":0.6264947023,"remaining_time":0.6264947023},
{"learn":[2.09224223],"iteration":500,"passed_time":0.6277147415,"remaining_time":0.6252088942},
{"learn":[2.080918326],"iteration":501,"passed_time":0.6292461325,"remaining_time":0.624232219},
{"learn":[2.07553897],"iteration":502,"passed_time":0.6303773425,"remaining_time":0.6228579309},
{"learn":[2.069742203],"iteration":503,"passed_time":0.6315143443,"remaining_time":0.621490307},
{"learn":[2.062388267],"iteration":504,"passed_time":0.6326522903,"remaining_time":0.6201245221},
{"learn":[2.050659675],"iteration":505,"passed_time":0.633898625,"remaining_time":0.618865456},
{"learn":[2.043770526],"iteration":506,"passed_time":0.6350694536,"remaining_time":0.617533019},
{"learn":[2.035621077],"iteration":507,"passed_time":0.6364624593,"remaining_time":0.6164163976},
{"learn":[2.020717682],"iteration":508,"passed_time":0.6377116801,"remaining_time":0.61515999},
{"learn":[2.012433625],"iteration":509,"passed_time":0.6389003787,"remaining_time":0.6138454619},
{"learn":[2.00732981],"iteration":510,"passed_time":0.6403480937,"remaining_time":0.6127792912},
{"learn":[1.998076463],"iteration":511,"passed_time":0.6416524653,"remaining_time":0.611575006},
{"learn":[1.992913382],"iteration":512,"passed_time":0.6428491634,"remaining_time":0.6102681142},
{"learn":[1.977335284],"iteration":513,"passed_time":0.644091039,"remaining_time":0.6090043676},
{"learn":[1.972987552],"iteration":514,"passed_time":0.6454648946,"remaining_time":0.6078649978},
{"learn":[1.963739169],"iteration":515,"passed_time":0.646646412,"remaining_time":0.6065443089},
{"learn":[1.958882747],"iteration":516,"passed_time":0.6478878357,"remaining_time":0.6052801251},
{"learn":[1.951623322],"iteration":517,"passed_time":0.6494158768,"remaining_time":0.604282727},
{"learn":[1.943096915],"iteration":518,"passed_time":0.6508322427,"remaining_time":0.6031797856},
{"learn":[1.931043842],"iteration":519,"passed_time":0.6522490961,"remaining_time":0.6020760887},
{"learn":[1.920678561],"iteration":520,"passed_time":0.6535876281,"remaining_time":0.6008991821},
{"learn":[1.912018668],"iteration":521,"passed_time":0.6548860958,"remaining_time":0.599684969},
{"learn":[1.907508347],"iteration":522,"passed_time":0.6560827283,"remaining_time":0.5983775552},
{"learn":[1.894139915],"iteration":523,"passed_time":0.6573831988,"remaining_time":0.5971648905},
{"learn":[1.88436445],"iteration":524,"passed_time":0.6585523296,"remaining_time":0.5958330601},
{"learn":[1.874419897],"iteration":525,"passed_time":0.6597723981,"remaining_time":0.5945477503},
{"learn":[1.865097771],"iteration":526,"passed_time":0.6612093111,"remaining_time":0.5934573134},
{"learn":[1.860702044],"iteration":527,"passed_time":0.6624902849,"remaining_time":0.5922261637},
{"learn":[1.853946653],"iteration":528,"passed_time":0.6637286476,"remaining_time":0.5909568866},
{"learn":[1.84585297],"iteration":529,"passed_time":0.6649174913,"remaining_time":0.589643813},
{"learn":[1.836730247],"iteration":530,"passed_time":0.6660984661,"remaining_time":0.5883242573},
{"learn":[1.826678684],"iteration":531,"passed_time":0.6672700151,"remaining_time":0.5869969306},
{"learn":[1.820350156],"iteration":532,"passed_time":0.6684043844,"remaining_time":0.5856376126},
{"learn":[1.81905265],"iteration":533,"passed_time":0.6695878253,"remaining_time":0.5843219599},
{"learn":[1.816254549],"iteration":534,"passed_time":0.6707330565,"remaining_time":0.5829735912},
{"learn":[1.807144241],"iteration":535,"passed_time":0.6720321743,"remaining_time":0.5817591956},
{"learn":[1.796302701],"iteration":536,"passed_time":0.6732881803,"remaining_time":0.5805073137},
{"learn":[1.788769737],"iteration":537,"passed_time":0.6744899522,"remaining_time":0.5792088437},
{"learn":[1.782512003],"iteration":538,"passed_time":0.6756847744,"remaining_time":0.5779047885},
{"learn":[1.771203985],"iteration":539,"passed_time":0.6768342162,"remaining_time":0.5765624805},
{"learn":[1.767593296],"iteration":540,"passed_time":0.678169189,"remaining_time":0.5753782953},
{"learn":[1.76527953],"iteration":541,"passed_time":0.6794560694,"remaining_time":0.5741529148},
{"learn":[1.761612964],"iteration":542,"passed_time":0.6806145687,"remaining_time":0.5728192594},
{"learn":[1.759110277],"iteration":543,"passed_time":0.6818120654,"remaining_time":0.5715189371},
{"learn":[1.749233426],"iteration":544,"passed_time":0.6830795401,"remaining_time":0.5702774142},
{"learn":[1.745729808],"iteration":545,"passed_time":0.6842271291,"remaining_time":0.568936111},
{"learn":[1.744378931],"iteration":546,"passed_time":0.6847618876,"remaining_time":0.5670879983},
{"learn":[1.735589147],"iteration":547,"passed_time":0.6859554908,"remaining_time":0.5657881055},
{"learn":[1.729323817],"iteration":548,"passed_time":0.6873020623,"remaining_time":0.5646142625},
{"learn":[1.724871464],"iteration":549,"passed_time":0.688489041,"remaining_time":0.5633092153},
{"learn":[1.717189963],"iteration":550,"passed_time":0.6897705115,"remaining_time":0.5620815965},
{"learn":[1.716274943],"iteration":551,"passed_time":0.6909069215,"remaining_time":0.5607360522},
{"learn":[1.709220849],"iteration":552,"passed_time":0.6922020139,"remaining_time":0.5595195302},
{"learn":[1.701112742],"iteration":553,"passed_time":0.6933481808,"remaining_time":0.5581828315},
{"learn":[1.693902317],"iteration":554,"passed_time":0.6945313896,"remaining_time":0.5568765196},
{"learn":[1.688307872],"iteration":555,"passed_time":0.6957729419,"remaining_time":0.5556172414},
{"learn":[1.68337278],"iteration":556,"passed_time":0.6969476355,"remaining_time":0.5543048519},
{"learn":[1.676581413],"iteration":557,"passed_time":0.6980887879,"remaining_time":0.5529663875},
{"learn":[1.665560045],"iteration":558,"passed_time":0.699271102,"remaining_time":0.5516611019},
{"learn":[1.663210011],"iteration":559,"passed_time":0.7004448906,"remaining_time":0.5503495569},
{"learn":[1.658264286],"iteration":560,"passed_time":0.7015701658,"remaining_time":0.5490005397},
{"learn":[1.656232475],"iteration":561,"passed_time":0.7027715256,"remaining_time":0.547711616},
{"learn":[1.647919791],"iteration":562,"passed_time":0.704067768,"remaining_time":0.5464966512},
{"learn":[1.644307414],"iteration":563,"passed_time":0.7053750052,"remaining_time":0.5452898977},
{"learn":[1.639058664],"iteration":564,"passed_time":0.7075700544,"remaining_time":0.5447663251},
{"learn":[1.637238529],"iteration":565,"passed_time":0.7092402775,"remaining_time":0.5438344177},
{"learn":[1.63306496],"iteration":566,"passed_time":0.7105685183,"remaining_time":0.542638745},
{"learn":[1.632159517],"iteration":567,"passed_time":0.7118430418,"remaining_time":0.5414017501},
{"learn":[1.624441194],"iteration":568,"passed_time":0.7131968053,"remaining_time":0.5402246451},
{"learn":[1.618669332],"iteration":569,"passed_time":0.7145237836,"remaining_time":0.5390267139},
{"learn":[1.614903991],"iteration":570,"passed_time":0.7159118379,"remaining_time":0.5378742179},
{"learn":[1.614006356],"iteration":571,"passed_time":0.7171325845,"remaining_time":0.5365957101},
{"learn":[1.608473656],"iteration":572,"passed_time":0.718351653,"remaining_time":0.5353161533},
{"learn":[1.60255487],"iteration":573,"passed_time":0.719683568,"remaining_time":0.5341205574},
{"learn":[1.5989573],"iteration":574,"passed_time":0.7210754129,"remaining_time":0.5329687834},
{"learn":[1.592015788],"iteration":575,"passed_time":0.7223119539,"remaining_time":0.531701855},
{"learn":[1.5833826],"iteration":576,"passed_time":0.724825028,"remaining_time":0.5313708611},
{"learn":[1.580781179],"iteration":577,"passed_time":0.7260513885,"remaining_time":0.5300928823},
{"learn":[1.5777026],"iteration":578,"passed_time":0.7274259984,"remaining_time":0.5289228762},
{"learn":[1.571735305],"iteration":579,"passed_time":0.7287074889,"remaining_time":0.5276847334},
{"learn":[1.564206036],"iteration":580,"passed_time":0.7299351319,"remaining_time":0.526407608},
{"learn":[1.560359481],"iteration":581,"passed_time":0.7311670323,"remaining_time":0.5251337104},
{"learn":[1.551305785],"iteration":582,"passed_time":0.7324331991,"remaining_time":0.5238844666},
{"learn":[1.545625467],"iteration":583,"passed_time":0.7340211476,"remaining_time":0.5228643791},
{"learn":[1.537988525],"iteration":584,"passed_time":0.7351856053,"remaining_time":0.5215419251},
{"learn":[1.533515129],"iteration":585,"passed_time":0.7363621996,"remaining_time":0.5202285847},
{"learn":[1.527350813],"iteration":586,"passed_time":0.7375156785,"remaining_time":0.5188994467},
{"learn":[1.519424754],"iteration":587,"passed_time":0.7387862278,"remaining_time":0.5176529351},
{"learn":[1.513673385],"iteration":588,"passed_time":0.7399609853,"remaining_time":0.5163394991},
{"learn":[1.508228137],"iteration":589,"passed_time":0.7411190563,"remaining_time":0.5150149374},
{"learn":[1.50495436],"iteration":590,"passed_time":0.742346556,"remaining_time":0.5137389872},
{"learn":[1.497797802],"iteration":591,"passed_time":0.7436612102,"remaining_time":0.5125232665},
{"learn":[1.492321268],"iteration":592,"passed_time":0.7450141734,"remaining_time":0.5113335052},
{"learn":[1.485991615],"iteration":593,"passed_time":0.7461984429,"remaining_time":0.5100278919},
{"learn":[1.482113076],"iteration":594,"passed_time":0.747633202,"remaining_time":0.5088931879},
{"learn":[1.476350163],"iteration":595,"passed_time":0.7492823648,"remaining_time":0.507902811},
{"learn":[1.470202562],"iteration":596,"passed_time":0.7504767894,"remaining_time":0.5066032598},
{"learn":[1.463349685],"iteration":597,"passed_time":0.7516833206,"remaining_time":0.5053121988},
{"learn":[1.458400647],"iteration":598,"passed_time":0.7531213825,"remaining_time":0.504176418},
{"learn":[1.454481824],"iteration":599,"passed_time":0.7543510097,"remaining_time":0.5029006732},
{"learn":[1.447841514],"iteration":600,"passed_time":0.7556127571,"remaining_time":0.5016464061},
{"learn":[1.440764174],"iteration":601,"passed_time":0.7571075091,"remaining_time":0.5005461605},
{"learn":[1.434263766],"iteration":602,"passed_time":0.7582889425,"remaining_time":0.4992383253},
{"learn":[1.431746598],"iteration":603,"passed_time":0.7590862162,"remaining_time":0.4976790424},
{"learn":[1.425942558],"iteration":604,"passed_time":0.7602484224,"remaining_time":0.4963605403},
{"learn":[1.42059909],"iteration":605,"passed_time":0.7615602849,"remaining_time":0.4951398552},
{"learn":[1.414931813],"iteration":606,"passed_time":0.7628722106,"remaining_time":0.4939189107},
{"learn":[1.412367008],"iteration":607,"passed_time":0.7641097055,"remaining_time":0.4926496786},
{"learn":[1.409260531],"iteration":608,"passed_time":0.7653833494,"remaining_time":0.4914037596},
{"learn":[1.403947253],"iteration":609,"passed_time":0.7666798672,"remaining_time":0.4901723741},
{"learn":[1.401383938],"iteration":610,"passed_time":0.7678434974,"remaining_time":0.488856171},
{"learn":[1.397553997],"iteration":611,"passed_time":0.7692748712,"remaining_time":0.4877102125},
{"learn":[1.392475988],"iteration":612,"passed_time":0.7704831138,"remaining_time":0.4864224552},
{"learn":[1.387196231],"iteration":613,"passed_time":0.7718164184,"remaining_time":0.485213579},
{"learn":[1.383187002],"iteration":614,"passed_time":0.7730333383,"remaining_time":0.4839314394},
{"learn":[1.376318135],"iteration":615,"passed_time":0.7741989299,"remaining_time":0.4826175148},
{"learn":[1.369835191],"iteration":616,"passed_time":0.7755690863,"remaining_time":0.4814310536},
{"learn":[1.365498877],"iteration":617,"passed_time":0.776720406,"remaining_time":0.4801087299},
{"learn":[1.359544006],"iteration":618,"passed_time":0.7779920346,"remaining_time":0.47886101},
{"learn":[1.353135399],"iteration":619,"passed_time":0.7793719851,"remaining_time":0.4776796038},
{"learn":[1.34853457],"iteration":620,"passed_time":0.7806565217,"remaining_time":0.4764393264},
{"learn":[1.346643846],"iteration":621,"passed_time":0.7818606176,"remaining_time":0.4751500216},
{"learn":[1.343248076],"iteration":622,"passed_time":0.7830436377,"remaining_time":0.4738482366},
{"learn":[1.339248336],"iteration":623,"passed_time":0.784271486,"remaining_time":0.4725738442},
{"learn":[1.334612851],"iteration":624,"passed_time":0.7854391344,"remaining_time":0.4712634806},
{"learn":[1.331496119],"iteration":625,"passed_time":0.7866161415,"remaining_time":0.4699591644},
{"learn":[1.326091522],"iteration":626,"passed_time":0.7878057422,"remaining_time":0.4686627462},
{"learn":[1.322794035],"iteration":627,"passed_time":0.7893814596,"remaining_time":0.4675953869},
{"learn":[1.317163941],"iteration":628,"passed_time":0.7908157002,"remaining_time":0.4664429646},
{"learn":[1.312513004],"iteration":629,"passed_time":0.7919981264,"remaining_time":0.4651417568},
{"learn":[1.305847438],"iteration":630,"passed_time":0.7932672572,"remaining_time":0.463891629},
{"learn":[1.301150173],"iteration":631,"passed_time":0.7945224093,"remaining_time":0.4626333016},
{"learn":[1.297471553],"iteration":632,"passed_time":0.7956956661,"remaining_time":0.4613275031},
{"learn":[1.292459315],"iteration":633,"passed_time":0.7969117417,"remaining_time":0.4600468414},
{"learn":[1.28940975],"iteration":634,"passed_time":0.7981156962,"remaining_time":0.4587594159},
{"learn":[1.284152279],"iteration":635,"passed_time":0.7994605381,"remaining_time":0.4575528866},
{"learn":[1.278875203],"iteration":636,"passed_time":0.8007198061,"remaining_time":0.456297158},
{"learn":[1.274690909],"iteration":637,"passed_time":0.8021104018,"remaining_time":0.4551159333},
{"learn":[1.26979526],"iteration":638,"passed_time":0.8033155663,"remaining_time":0.4538292949},
{"learn":[1.266203851],"iteration":639,"passed_time":0.8046187732,"remaining_time":0.4525980599},
{"learn":[1.263048063],"iteration":640,"passed_time":0.8058194663,"remaining_time":0.4513091863},
{"learn":[1.257242694],"iteration":641,"passed_time":0.8070456599,"remaining_time":0.4500348073},
{"learn":[1.253673312],"iteration":642,"passed_time":0.8082266802,"remaining_time":0.4487354974},
{"learn":[1.248860379],"iteration":643,"passed_time":0.8094202195,"remaining_time":0.4474434754},
{"learn":[1.246065697],"iteration":644,"passed_time":0.810651947,"remaining_time":0.446172777},
{"learn":[1.238856062],"iteration":645,"passed_time":0.8118151415,"remaining_time":0.4448646441},
{"learn":[1.234759777],"iteration":646,"passed_time":0.8131619708,"remaining_time":0.4436571494},
{"learn":[1.231376865],"iteration":647,"passed_time":0.8143763304,"remaining_time":0.4423772659},
{"learn":[1.228645545],"iteration":648,"passed_time":0.815652635,"remaining_time":0.4411310861},
{"learn":[1.224436029],"iteration":649,"passed_time":0.8169245682,"remaining_time":0.4398824598},
{"learn":[1.219811202],"iteration":650,"passed_time":0.8181233517,"remaining_time":0.4385945464},
{"learn":[1.214245223],"iteration":651,"passed_time":0.819364704,"remaining_time":0.4373296273},
{"learn":[1.206958211],"iteration":652,"passed_time":0.8207247467,"remaining_time":0.4361278516},
{"learn":[1.202287846],"iteration":653,"passed_time":0.821903313,"remaining_time":0.4348295815},
{"learn":[1.198364812],"iteration":654,"passed_time":0.8232512516,"remaining_time":0.4336208883},
{"learn":[1.195834589],"iteration":655,"passed_time":0.8245447219,"remaining_time":0.4323832078},
{"learn":[1.191352009],"iteration":656,"passed_time":0.8257373573,"remaining_time":0.4310927147},
{"learn":[1.188873375],"iteration":657,"passed_time":0.8269218489,"remaining_time":0.4297982862},
{"learn":[1.18552186],"iteration":658,"passed_time":0.8280960471,"remaining_time":0.428498865},
{"learn":[1.181470475],"iteration":659,"passed_time":0.8293079018,"remaining_time":0.4272192221},
{"learn":[1.178756847],"iteration":660,"passed_time":0.8304552808,"remaining_time":0.4259067174},
{"learn":[1.175514259],"iteration":661,"passed_time":0.831621107,"remaining_time":0.4246041302},
{"learn":[1.170926925],"iteration":662,"passed_time":0.8328087011,"remaining_time":0.42331302},
{"learn":[1.167853221],"iteration":663,"passed_time":0.8339482149,"remaining_time":0.4219978919},
{"learn":[1.162813627],"iteration":664,"passed_time":0.8351115912,"remaining_time":0.4206953129},
{"learn":[1.159653015],"iteration":665,"passed_time":0.8362502661,"remaining_time":0.4193807641},
{"learn":[1.156601003],"iteration":666,"passed_time":0.8374119578,"remaining_time":0.4180782338},
{"learn":[1.151849797],"iteration":667,"passed_time":0.8385855895,"remaining_time":0.4167820595},
{"learn":[1.149215448],"iteration":668,"passed_time":0.8398273172,"remaining_time":0.4155199432},
{"learn":[1.143773946],"iteration":669,"passed_time":0.8409786901,"remaining_time":0.4142133847},
{"learn":[1.140273569],"iteration":670,"passed_time":0.8421134369,"remaining_time":0.4128991367},
{"learn":[1.137417148],"iteration":671,"passed_time":0.8433663973,"remaining_time":0.4116431225},
{"learn":[1.133721079],"iteration":672,"passed_time":0.8445236797,"remaining_time":0.4103406289},
{"learn":[1.130328884],"iteration":673,"passed_time":0.8456500181,"remaining_time":0.4090235993},
{"learn":[1.126644351],"iteration":674,"passed_time":0.8467878984,"remaining_time":0.4077126918},
{"learn":[1.123317302],"iteration":675,"passed_time":0.8479698907,"remaining_time":0.4064234388},
{"learn":[1.119604099],"iteration":676,"passed_time":0.8490856986,"remaining_time":0.4051029256},
{"learn":[1.116033714],"iteration":677,"passed_time":0.8502792179,"remaining_time":0.4038199235},
{"learn":[1.113404178],"iteration":678,"passed_time":0.8515175503,"remaining_time":0.4025583706},
{"learn":[1.107837657],"iteration":679,"passed_time":0.8527634564,"remaining_time":0.4013004501},
{"learn":[1.10244549],"iteration":680,"passed_time":0.8541926832,"remaining_time":0.4001284375},
{"learn":[1.099349578],"iteration":681,"passed_time":0.8553498503,"remaining_time":0.3988288158},
{"learn":[1.094029448],"iteration":682,"passed_time":0.8565865952,"remaining_time":0.3975665457},
{"learn":[1.089843555],"iteration":683,"passed_time":0.8578777284,"remaining_time":0.3963294769},
{"learn":[1.089031959],"iteration":684,"passed_time":0.8590244793,"remaining_time":0.3950258554},
{"learn":[1.086362505],"iteration":685,"passed_time":0.8601640078,"remaining_time":0.3937193855},
{"learn":[1.08050094],"iteration":686,"passed_time":0.8613298994,"remaining_time":0.3924254127},
{"learn":[1.078508173],"iteration":687,"passed_time":0.8625410972,"remaining_time":0.3911523581},
{"learn":[1.074081452],"iteration":688,"passed_time":0.8637321026,"remaining_time":0.3898703685},
{"learn":[1.071005295],"iteration":689,"passed_time":0.8649689536,"remaining_time":0.38860924},
{"learn":[1.068777205],"iteration":690,"passed_time":0.8664378993,"remaining_time":0.3874519695},
{"learn":[1.066150931],"iteration":691,"passed_time":0.8676224406,"remaining_time":0.3861672134},
{"learn":[1.060741976],"iteration":692,"passed_time":0.868817178,"remaining_time":0.3848872636},
{"learn":[1.057489205],"iteration":693,"passed_time":0.8701136965,"remaining_time":0.3836524368},
{"learn":[1.054001339],"iteration":694,"passed_time":0.871287724,"remaining_time":0.3823636774},
{"learn":[1.049549342],"iteration":695,"passed_time":0.8724551916,"remaining_time":0.3810723825},
{"learn":[1.047297725],"iteration":696,"passed_time":0.8737058674,"remaining_time":0.3798176152},
{"learn":[1.043460036],"iteration":697,"passed_time":0.8749717985,"remaining_time":0.3785694601},
{"learn":[1.041294552],"iteration":698,"passed_time":0.8761341634,"remaining_time":0.3772766569},
{"learn":[1.037329064],"iteration":699,"passed_time":0.8772686645,"remaining_time":0.3759722848},
{"learn":[1.034515002],"iteration":700,"passed_time":0.8785224812,"remaining_time":0.3747192894},
{"learn":[1.03108313],"iteration":701,"passed_time":0.8799646074,"remaining_time":0.3735462293},
{"learn":[1.028370286],"iteration":702,"passed_time":0.8811289936,"remaining_time":0.3722550656},
{"learn":[1.026838032],"iteration":703,"passed_time":0.8823209044,"remaining_time":0.3709758348},
{"learn":[1.023669192],"iteration":704,"passed_time":0.8836227045,"remaining_time":0.3697428338},
{"learn":[1.018993559],"iteration":705,"passed_time":0.8851128745,"remaining_time":0.3685880809},
{"learn":[1.014011649],"iteration":706,"passed_time":0.8862926008,"remaining_time":0.3673037228},
{"learn":[1.011921788],"iteration":707,"passed_time":0.8874410652,"remaining_time":0.366006767},
{"learn":[1.010213664],"iteration":708,"passed_time":0.8886109181,"remaining_time":0.3647190087},
{"learn":[1.007428134],"iteration":709,"passed_time":0.8898646327,"remaining_time":0.3634658359},
{"learn":[1.003580695],"iteration":710,"passed_time":0.8910111918,"remaining_time":0.3621691061},
{"learn":[1.002111215],"iteration":711,"passed_time":0.8922526627,"remaining_time":0.3609111894},
{"learn":[1.000386101],"iteration":712,"passed_time":0.8934330987,"remaining_time":0.3596287508},
{"learn":[0.9987582434],"iteration":713,"passed_time":0.8947744667,"remaining_time":0.3584110609},
{"learn":[0.9959831006],"iteration":714,"passed_time":0.8960440981,"remaining_time":0.3571644307},
{"learn":[0.9934203887],"iteration":715,"passed_time":0.8972315265,"remaining_time":0.3558851306},
{"learn":[0.9917074665],"iteration":716,"passed_time":0.8984604923,"remaining_time":0.3546224816},
{"learn":[0.9884290367],"iteration":717,"passed_time":0.8998661709,"remaining_time":0.3534293317},
{"learn":[0.9870254222],"iteration":718,"passed_time":0.901037392,"remaining_time":0.3521439599},
{"learn":[0.984638161],"iteration":719,"passed_time":0.9028182241,"remaining_time":0.3510959761},
{"learn":[0.9825173325],"iteration":720,"passed_time":0.904142831,"remaining_time":0.3498694173},
{"learn":[0.9796536656],"iteration":721,"passed_time":0.9052736597,"remaining_time":0.3485679742},
{"learn":[0.9762002336],"iteration":722,"passed_time":0.9064098536,"remaining_time":0.3472690587},
{"learn":[0.9736662133],"iteration":723,"passed_time":0.9076458353,"remaining_time":0.3460086333},
{"learn":[0.9718751895],"iteration":724,"passed_time":0.9087571936,"remaining_time":0.3447010045},
{"learn":[0.9695561631],"iteration":725,"passed_time":0.9098714025,"remaining_time":0.3433949921},
{"learn":[0.967565018],"iteration":726,"passed_time":0.9109988144,"remaining_time":0.3420944654},
{"learn":[0.9634693539],"iteration":727,"passed_time":0.9121418775,"remaining_time":0.3408002619},
{"learn":[0.9608887991],"iteration":728,"passed_time":0.9132587221,"remaining_time":0.3394967266},
{"learn":[0.9577706845],"iteration":729,"passed_time":0.9143929032,"remaining_time":0.3382001149},
{"learn":[0.9543877183],"iteration":730,"passed_time":0.9155320392,"remaining_time":0.3369057709},
{"learn":[0.9507947379],"iteration":731,"passed_time":0.9166529334,"remaining_time":0.3356051723},
{"learn":[0.9493869201],"iteration":732,"passed_time":0.9178450455,"remaining_time":0.3343310057},
{"learn":[0.947270579],"iteration":733,"passed_time":0.9189648279,"remaining_time":0.3330308505},
{"learn":[0.9451231022],"iteration":734,"passed_time":0.9215801477,"remaining_time":0.3322703934},
{"learn":[0.9412915355],"iteration":735,"passed_time":0.9230037503,"remaining_time":0.3310774322},
{"learn":[0.9396391684],"iteration":736,"passed_time":0.9242696961,"remaining_time":0.3298275849},
{"learn":[0.9366780264],"iteration":737,"passed_time":0.9255716745,"remaining_time":0.3285904861},
{"learn":[0.9348831411],"iteration":738,"passed_time":0.9268780788,"remaining_time":0.3273547748},
{"learn":[0.9334925784],"iteration":739,"passed_time":0.9281814193,"remaining_time":0.326117796},
{"learn":[0.931211001],"iteration":740,"passed_time":0.9294484266,"remaining_time":0.3248679386},
{"learn":[0.9291491541],"iteration":741,"passed_time":0.9306993309,"remaining_time":0.3236124358},
{"learn":[0.9266889527],"iteration":742,"passed_time":0.9318981261,"remaining_time":0.3223389212},
{"learn":[0.9248094014],"iteration":743,"passed_time":0.9331406663,"remaining_time":0.3210806594},
{"learn":[0.9223210806],"iteration":744,"passed_time":0.9343973898,"remaining_time":0.3198272945},
{"learn":[0.920165476],"iteration":745,"passed_time":0.9356419706,"remaining_time":0.3185697863},
{"learn":[0.9165986503],"iteration":746,"passed_time":0.9368677479,"remaining_time":0.3173059441},
{"learn":[0.9136148753],"iteration":747,"passed_time":0.938042774,"remaining_time":0.3160251057},
{"learn":[0.9101480459],"iteration":748,"passed_time":0.9392285241,"remaining_time":0.3147481436},
{"learn":[0.9068382234],"iteration":749,"passed_time":0.94050922,"remaining_time":0.3135030733},
{"learn":[0.9043611896],"iteration":750,"passed_time":0.9417313138,"remaining_time":0.3122384782},
{"learn":[0.9008029968],"iteration":751,"passed_time":0.9429435245,"remaining_time":0.3109707368},
{"learn":[0.8981577799],"iteration":752,"passed_time":0.9441891668,"remaining_time":0.3097141092},
{"learn":[0.8957514656],"iteration":753,"passed_time":0.9453606143,"remaining_time":0.3084333039},
{"learn":[0.8950903088],"iteration":754,"passed_time":0.9465506022,"remaining_time":0.3071588047},
{"learn":[0.8924610711],"iteration":755,"passed_time":0.9478983887,"remaining_time":0.3059354588},
{"learn":[0.8902332173],"iteration":756,"passed_time":0.9491943465,"remaining_time":0.3046951469},
{"learn":[0.8886334261],"iteration":757,"passed_time":0.9503804059,"remaining_time":0.3034196019},
{"learn":[0.8866248282],"iteration":758,"passed_time":0.9515600894,"remaining_time":0.3021422682},
{"learn":[0.8859524189],"iteration":759,"passed_time":0.9527054206,"remaining_time":0.3008543433},
{"learn":[0.8843152849],"iteration":760,"passed_time":0.9538687129,"remaining_time":0.2995724342},
{"learn":[0.8823701093],"iteration":761,"passed_time":0.9550713513,"remaining_time":0.2983031255},
{"learn":[0.8785119301],"iteration":762,"passed_time":0.9562969657,"remaining_time":0.2970411283},
{"learn":[0.8761655017],"iteration":763,"passed_time":0.9574984063,"remaining_time":0.295771759},
{"learn":[0.8745904896],"iteration":764,"passed_time":0.9586869618,"remaining_time":0.2944986092},
{"learn":[0.8714852162],"iteration":765,"passed_time":0.9598550072,"remaining_time":0.2932194147},
{"learn":[0.8701824669],"iteration":766,"passed_time":0.9611488325,"remaining_time":0.2919787197},
{"learn":[0.8667119928],"iteration":767,"passed_time":0.9624854653,"remaining_time":0.2907508176},
{"learn":[0.8654810836],"iteration":768,"passed_time":0.9638318985,"remaining_time":0.2895255768},
{"learn":[0.8641597926],"iteration":769,"passed_time":0.9652365547,"remaining_time":0.2883174124},
{"learn":[0.8625798319],"iteration":770,"passed_time":0.9669139716,"remaining_time":0.2871897529},
{"learn":[0.8599188818],"iteration":771,"passed_time":0.9683198998,"remaining_time":0.2859804886},
{"learn":[0.8574774904],"iteration":772,"passed_time":0.9695967883,"remaining_time":0.2847328214},
{"learn":[0.8558506683],"iteration":773,"passed_time":0.9707904844,"remaining_time":0.2834607874},
{"learn":[0.8530730008],"iteration":774,"passed_time":0.9721124085,"remaining_time":0.2822261831},
{"learn":[0.8509336592],"iteration":775,"passed_time":0.9733953204,"remaining_time":0.2809800925},
{"learn":[0.8485645249],"iteration":776,"passed_time":0.9746061108,"remaining_time":0.2797132081},
{"learn":[0.8478481255],"iteration":777,"passed_time":0.9758689488,"remaining_time":0.2784613196},
{"learn":[0.8461469031],"iteration":778,"passed_time":0.9770413085,"remaining_time":0.2771837345},
{"learn":[0.8424597088],"iteration":779,"passed_time":0.9782145353,"remaining_time":0.2759066638},
{"learn":[0.841453797],"iteration":780,"passed_time":0.9794100445,"remaining_time":0.2746361072},
{"learn":[0.8390931577],"iteration":781,"passed_time":0.980606438,"remaining_time":0.2733659891},
{"learn":[0.8371274378],"iteration":782,"passed_time":0.981991921,"remaining_time":0.2721484634},
{"learn":[0.8337987777],"iteration":783,"passed_time":0.9833928218,"remaining_time":0.270934757},
{"learn":[0.831990966],"iteration":784,"passed_time":0.9846286728,"remaining_time":0.269675369},
{"learn":[0.8303013532],"iteration":785,"passed_time":0.9858890655,"remaining_time":0.2684227227},
{"learn":[0.8286901985],"iteration":786,"passed_time":0.9873043929,"remaining_time":0.2672119894},
{"learn":[0.8271227709],"iteration":787,"passed_time":0.9885076942,"remaining_time":0.2659436944},
{"learn":[0.8237252367],"iteration":788,"passed_time":0.9897480851,"remaining_time":0.2646854828},
{"learn":[0.8219410404],"iteration":789,"passed_time":0.9909992233,"remaining_time":0.2634301733},
{"learn":[0.8215579141],"iteration":790,"passed_time":0.9922438095,"remaining_time":0.2621731431},
{"learn":[0.8181000406],"iteration":791,"passed_time":0.993493311,"remaining_time":0.2609174352},
{"learn":[0.8166525184],"iteration":792,"passed_time":0.9948353458,"remaining_time":0.2596858973},
{"learn":[0.8136103683],"iteration":793,"passed_time":0.9960861987,"remaining_time":0.2584304243},
{"learn":[0.8113992999],"iteration":794,"passed_time":0.9972982958,"remaining_time":0.2571649694},
{"learn":[0.8081604371],"iteration":795,"passed_time":0.9988005438,"remaining_time":0.2559740087},
{"learn":[0.8069231442],"iteration":796,"passed_time":0.9999893471,"remaining_time":0.2547024309},
{"learn":[0.8041625851],"iteration":797,"passed_time":1.001434685,"remaining_time":0.253495998},
{"learn":[0.8034587616],"iteration":798,"passed_time":1.002669122,"remaining_time":0.2522359117},
{"learn":[0.8016126154],"iteration":799,"passed_time":1.003901793,"remaining_time":0.2509754483},
{"learn":[0.7989908325],"iteration":800,"passed_time":1.00515433,"remaining_time":0.2497199896},
{"learn":[0.7962885043],"iteration":801,"passed_time":1.006332672,"remaining_time":0.2484462208},
{"learn":[0.7954153406],"iteration":802,"passed_time":1.007490934,"remaining_time":0.2471677633},
{"learn":[0.7935492414],"iteration":803,"passed_time":1.00870166,"remaining_time":0.2459023948},
{"learn":[0.7909142019],"iteration":804,"passed_time":1.009914933,"remaining_time":0.2446377789},
{"learn":[0.788132084],"iteration":805,"passed_time":1.011156316,"remaining_time":0.2433800561},
{"learn":[0.7871196804],"iteration":806,"passed_time":1.012294181,"remaining_time":0.2420976169},
{"learn":[0.7863009702],"iteration":807,"passed_time":1.013453296,"remaining_time":0.2408205852},
{"learn":[0.7833164117],"iteration":808,"passed_time":1.014679557,"remaining_time":0.2395596977},
{"learn":[0.7821218824],"iteration":809,"passed_time":1.015872369,"remaining_time":0.2382910496},
{"learn":[0.7802511314],"iteration":810,"passed_time":1.017011036,"remaining_time":0.2370099702},
{"learn":[0.7781700948],"iteration":811,"passed_time":1.018198122,"remaining_time":0.2357404518},
{"learn":[0.777319683],"iteration":812,"passed_time":1.019370748,"remaining_time":0.2344678104},
{"learn":[0.7759613708],"iteration":813,"passed_time":1.020754737,"remaining_time":0.2332437114},
{"learn":[0.7748598627],"iteration":814,"passed_time":1.022134197,"remaining_time":0.2320181919},
{"learn":[0.772634629],"iteration":815,"passed_time":1.023320595,"remaining_time":0.2307487617},
{"learn":[0.7704552614],"iteration":816,"passed_time":1.02486445,"remaining_time":0.2295596014},
{"learn":[0.7687428715],"iteration":817,"passed_time":1.026159515,"remaining_time":0.2283142196},
{"learn":[0.7665917339],"iteration":818,"passed_time":1.027346699,"remaining_time":0.2270448748},
{"learn":[0.7635400179],"iteration":819,"passed_time":1.028502414,"remaining_time":0.2257688227},
{"learn":[0.7612983076],"iteration":820,"passed_time":1.029636908,"remaining_time":0.2244884368},
{"learn":[0.7583123679],"iteration":821,"passed_time":1.0309614,"remaining_time":0.2232495489},
{"learn":[0.7560034477],"iteration":822,"passed_time":1.032165123,"remaining_time":0.2219844796},
{"learn":[0.7536162135],"iteration":823,"passed_time":1.033329648,"remaining_time":0.220711187},
{"learn":[0.7516685482],"iteration":824,"passed_time":1.034557346,"remaining_time":0.2194515583},
{"learn":[0.7488477309],"iteration":825,"passed_time":1.035871966,"remaining_time":0.2182103173},
{"learn":[0.7470054854],"iteration":826,"passed_time":1.037028199,"remaining_time":0.216935766},
{"learn":[0.7450319305],"iteration":827,"passed_time":1.038327299,"remaining_time":0.2156911781},
{"learn":[0.7434686497],"iteration":828,"passed_time":1.039537717,"remaining_time":0.214428166},
{"learn":[0.740400959],"iteration":829,"passed_time":1.04073567,"remaining_time":0.2131627276},
{"learn":[0.7377740429],"iteration":830,"passed_time":1.041980588,"remaining_time":0.2119070029},
{"learn":[0.7374760611],"iteration":831,"passed_time":1.044254902,"remaining_time":0.2108591628},
{"learn":[0.7362509913],"iteration":832,"passed_time":1.045560395,"remaining_time":0.2096141489},
{"learn":[0.7343972634],"iteration":833,"passed_time":1.046918659,"remaining_time":0.2083794933},
{"learn":[0.7339074146],"iteration":834,"passed_time":1.048307193,"remaining_time":0.2071505231},
{"learn":[0.7320829184],"iteration":835,"passed_time":1.049493079,"remaining_time":0.2058814174},
{"learn":[0.7308652385],"iteration":836,"passed_time":1.050714425,"remaining_time":0.204619416},
{"learn":[0.7292478448],"iteration":837,"passed_time":1.052007485,"remaining_time":0.2033713754},
{"learn":[0.7272428191],"iteration":838,"passed_time":1.053334767,"remaining_time":0.2021297944},
{"learn":[0.7259458285],"iteration":839,"passed_time":1.05471466,"remaining_time":0.2008980305},
{"learn":[0.7244812213],"iteration":840,"passed_time":1.055888367,"remaining_time":0.1996269326},
{"learn":[0.7223476441],"iteration":841,"passed_time":1.057074418,"remaining_time":0.1983583824},
{"learn":[0.7207238877],"iteration":842,"passed_time":1.058281501,"remaining_time":0.1970939451},
{"learn":[0.7187877638],"iteration":843,"passed_time":1.059891456,"remaining_time":0.195904108},
{"learn":[0.7164605395],"iteration":844,"passed_time":1.061059752,"remaining_time":0.1946322622},
{"learn":[0.7145947818],"iteration":845,"passed_time":1.0622624,"remaining_time":0.1933669145},
{"learn":[0.7121829503],"iteration":846,"passed_time":1.063587859,"remaining_time":0.1921238989},
{"learn":[0.7117840273],"iteration":847,"passed_time":1.064795828,"remaining_time":0.1908596296},
{"learn":[0.7097195761],"iteration":848,"passed_time":1.066000153,"remaining_time":0.1895948447},
{"learn":[0.7077260186],"iteration":849,"passed_time":1.067218685,"remaining_time":0.1883327091},
{"learn":[0.7057295914],"iteration":850,"passed_time":1.06849269,"remaining_time":0.1870803888},
{"learn":[0.7041986528],"iteration":851,"passed_time":1.069668607,"remaining_time":0.1858109786},
{"learn":[0.7019665619],"iteration":852,"passed_time":1.070854102,"remaining_time":0.1845434384},
{"learn":[0.699791756],"iteration":853,"passed_time":1.072133399,"remaining_time":0.1832921267},
{"learn":[0.6971966342],"iteration":854,"passed_time":1.073403985,"remaining_time":0.1820392723},
{"learn":[0.6954576272],"iteration":855,"passed_time":1.07496868,"remaining_time":0.1808358527},
{"learn":[0.6937640957],"iteration":856,"passed_time":1.076185418,"remaining_time":0.1795735295},
{"learn":[0.6919943678],"iteration":857,"passed_time":1.077467493,"remaining_time":0.1783221259},
{"learn":[0.6898762475],"iteration":858,"passed_time":1.078672762,"remaining_time":0.1770580436},
{"learn":[0.6878723158],"iteration":859,"passed_time":1.079878125,"remaining_time":0.1757941134},
{"learn":[0.6867871399],"iteration":860,"passed_time":1.081073757,"remaining_time":0.1745287483},
{"learn":[0.6841184313],"iteration":861,"passed_time":1.082367874,"remaining_time":0.1732793117},
{"learn":[0.6823144296],"iteration":862,"passed_time":1.083603105,"remaining_time":0.1720204233},
{"learn":[0.6811842224],"iteration":863,"passed_time":1.084792921,"remaining_time":0.1707544413},
{"learn":[0.679923908],"iteration":864,"passed_time":1.08597097,"remaining_time":0.1694867988},
{"learn":[0.6793900343],"iteration":865,"passed_time":1.0872684,"remaining_time":0.1682378355},
{"learn":[0.6774931104],"iteration":866,"passed_time":1.088486103,"remaining_time":0.1669765302},
{"learn":[0.675912963],"iteration":867,"passed_time":1.089601578,"remaining_time":0.1656997791},
{"learn":[0.6747329937],"iteration":868,"passed_time":1.090745604,"remaining_time":0.1644277033},
{"learn":[0.6729349858],"iteration":869,"passed_time":1.091933578,"remaining_time":0.1631624886},
{"learn":[0.6714502108],"iteration":870,"passed_time":1.093202148,"remaining_time":0.1619093881},
{"learn":[0.6710617395],"iteration":871,"passed_time":1.094333119,"remaining_time":0.1606360542},
{"learn":[0.6697452108],"iteration":872,"passed_time":1.095484348,"remaining_time":0.1593659934},
{"learn":[0.6676006006],"iteration":873,"passed_time":1.09667822,"remaining_time":0.158102352},
{"learn":[0.6653929034],"iteration":874,"passed_time":1.097836054,"remaining_time":0.1568337221},
{"learn":[0.6641396982],"iteration":875,"passed_time":1.099047465,"remaining_time":0.1555729289},
{"learn":[0.6631130592],"iteration":876,"passed_time":1.100233722,"remaining_time":0.1543087204},
{"learn":[0.6629298259],"iteration":877,"passed_time":1.1016041,"remaining_time":0.1530702736},
{"learn":[0.6622229147],"iteration":878,"passed_time":1.102751726,"remaining_time":0.1518008633},
{"learn":[0.6609928243],"iteration":879,"passed_time":1.103865927,"remaining_time":0.1505271718},
{"learn":[0.659693499],"iteration":880,"passed_time":1.105025626,"remaining_time":0.1492599881},
{"learn":[0.6586649164],"iteration":881,"passed_time":1.106166206,"remaining_time":0.1479904901},
{"learn":[0.6572442617],"iteration":882,"passed_time":1.107339616,"remaining_time":0.1467256342},
{"learn":[0.6550031191],"iteration":883,"passed_time":1.108509632,"remaining_time":0.14546054},
{"learn":[0.6528308245],"iteration":884,"passed_time":1.109635701,"remaining_time":0.1441899499},
{"learn":[0.6504370401],"iteration":885,"passed_time":1.110800517,"remaining_time":0.1429246715},
{"learn":[0.6491120258],"iteration":886,"passed_time":1.112824479,"remaining_time":0.1417690711},
{"learn":[0.6477259477],"iteration":887,"passed_time":1.114006146,"remaining_time":0.1405052796},
{"learn":[0.6462925936],"iteration":888,"passed_time":1.115178691,"remaining_time":0.139240534},
{"learn":[0.6448979251],"iteration":889,"passed_time":1.116305482,"remaining_time":0.1379703405},
{"learn":[0.6434856477],"iteration":890,"passed_time":1.117444266,"remaining_time":0.136701936},
{"learn":[0.6421338648],"iteration":891,"passed_time":1.118581636,"remaining_time":0.135433651},
{"learn":[0.6402881798],"iteration":892,"passed_time":1.119769926,"remaining_time":0.1341717604},
{"learn":[0.6383372048],"iteration":893,"passed_time":1.120966757,"remaining_time":0.1329110473},
{"learn":[0.6366884083],"iteration":894,"passed_time":1.122104764,"remaining_time":0.1316435756},
{"learn":[0.6353281697],"iteration":895,"passed_time":1.123366776,"remaining_time":0.1303907865},
{"learn":[0.6331601666],"iteration":896,"passed_time":1.12489686,"remaining_time":0.1291687587},
{"learn":[0.6326523408],"iteration":897,"passed_time":1.12611699,"remaining_time":0.1279108385},
{"learn":[0.6313101059],"iteration":898,"passed_time":1.127288127,"remaining_time":0.1266474981},
{"learn":[0.630136065],"iteration":899,"passed_time":1.12865113,"remaining_time":0.1254056811},
{"learn":[0.6285129213],"iteration":900,"passed_time":1.130028266,"remaining_time":0.124165148},
{"learn":[0.6277416946],"iteration":901,"passed_time":1.131452,"remaining_time":0.1229293748},
{"learn":[0.6263466946],"iteration":902,"passed_time":1.13261916,"remaining_time":0.121665624},
{"learn":[0.6249013098],"iteration":903,"passed_time":1.133795371,"remaining_time":0.1204030482},
{"learn":[0.6242368673],"iteration":904,"passed_time":1.135003091,"remaining_time":0.1191439708},
{"learn":[0.6228870457],"iteration":905,"passed_time":1.136179821,"remaining_time":0.1178817916},
{"learn":[0.6224341427],"iteration":906,"passed_time":1.137364104,"remaining_time":0.1166205752},
{"learn":[0.6220769267],"iteration":907,"passed_time":1.138632779,"remaining_time":0.115368079},
{"learn":[0.62145413],"iteration":908,"passed_time":1.140032014,"remaining_time":0.1141286175},
{"learn":[0.6191767027],"iteration":909,"passed_time":1.141237961,"remaining_time":0.1128696884},
{"learn":[0.6188514637],"iteration":910,"passed_time":1.142386267,"remaining_time":0.1116052446},
{"learn":[0.6182890536],"iteration":911,"passed_time":1.143661105,"remaining_time":0.1103532645},
{"learn":[0.6167626919],"iteration":912,"passed_time":1.144859558,"remaining_time":0.1090939557},
{"learn":[0.615022528],"iteration":913,"passed_time":1.146029119,"remaining_time":0.1078320615},
{"learn":[0.6137963011],"iteration":914,"passed_time":1.147177193,"remaining_time":0.1065683731},
{"learn":[0.6128269177],"iteration":915,"passed_time":1.148481649,"remaining_time":0.1053192779},
{"learn":[0.6115202555],"iteration":916,"passed_time":1.149678807,"remaining_time":0.10406035},
{"learn":[0.6101372006],"iteration":917,"passed_time":1.150893225,"remaining_time":0.1028030985},
{"learn":[0.6086471119],"iteration":918,"passed_time":1.152449279,"remaining_time":0.1015760518},
{"learn":[0.6072129185],"iteration":919,"passed_time":1.153812638,"remaining_time":0.1003315337},
{"learn":[0.6069322749],"iteration":920,"passed_time":1.154940982,"remaining_time":0.09906659886},
{"learn":[0.6052970251],"iteration":921,"passed_time":1.156118127,"remaining_time":0.09780608886},
{"learn":[0.6040444118],"iteration":922,"passed_time":1.157570217,"remaining_time":0.09656869629},
{"learn":[0.6023346131],"iteration":923,"passed_time":1.158980623,"remaining_time":0.09532741051},
{"learn":[0.60064208],"iteration":924,"passed_time":1.161048334,"remaining_time":0.09413905409},
{"learn":[0.5989036995],"iteration":925,"passed_time":1.162983394,"remaining_time":0.09293819777},
{"learn":[0.597607048],"iteration":926,"passed_time":1.164222389,"remaining_time":0.09168094328},
{"learn":[0.5965455865],"iteration":927,"passed_time":1.165470389,"remaining_time":0.09042442674},
{"learn":[0.5951950733],"iteration":928,"passed_time":1.167885307,"remaining_time":0.08925711171},
{"learn":[0.5940952968],"iteration":929,"passed_time":1.169205864,"remaining_time":0.08800474249},
{"learn":[0.5920788383],"iteration":930,"passed_time":1.17043659,"remaining_time":0.08674556898},
{"learn":[0.5907310591],"iteration":931,"passed_time":1.171870853,"remaining_time":0.08550130687},
{"learn":[0.5897160545],"iteration":932,"passed_time":1.173167831,"remaining_time":0.08424677884},
{"learn":[0.5882502263],"iteration":933,"passed_time":1.174454515,"remaining_time":0.08299143254},
{"learn":[0.5872931748],"iteration":934,"passed_time":1.175690622,"remaining_time":0.08173250314},
{"learn":[0.5859741356],"iteration":935,"passed_time":1.176945,"remaining_time":0.08047487182},
{"learn":[0.5838871184],"iteration":936,"passed_time":1.178330343,"remaining_time":0.07922605291},
{"learn":[0.5826789605],"iteration":937,"passed_time":1.179570064,"remaining_time":0.07796731768},
{"learn":[0.5809194445],"iteration":938,"passed_time":1.180786977,"remaining_time":0.07670714119},
{"learn":[0.5806209767],"iteration":939,"passed_time":1.182037274,"remaining_time":0.07544918771},
{"learn":[0.5792569003],"iteration":940,"passed_time":1.183274058,"remaining_time":0.07419040323},
{"learn":[0.5775838198],"iteration":941,"passed_time":1.184508449,"remaining_time":0.07293151807},
{"learn":[0.5759459626],"iteration":942,"passed_time":1.185762282,"remaining_time":0.07167386007},
{"learn":[0.57447507],"iteration":943,"passed_time":1.186974772,"remaining_time":0.07041375765},
{"learn":[0.5732966173],"iteration":944,"passed_time":1.188192962,"remaining_time":0.06915408772},
{"learn":[0.5718795449],"iteration":945,"passed_time":1.189442705,"remaining_time":0.06789630665},
{"learn":[0.570690314],"iteration":946,"passed_time":1.190674236,"remaining_time":0.06663752323},
{"learn":[0.5697420089],"iteration":947,"passed_time":1.191893499,"remaining_time":0.06537812441},
{"learn":[0.5684629429],"iteration":948,"passed_time":1.193064529,"remaining_time":0.06411621808},
{"learn":[0.5672750776],"iteration":949,"passed_time":1.194304074,"remaining_time":0.06285810917},
{"learn":[0.5667630791],"iteration":950,"passed_time":1.19559475,"remaining_time":0.06160267376},
{"learn":[0.5660407568],"iteration":951,"passed_time":1.196966048,"remaining_time":0.0603512293},
{"learn":[0.5649669762],"iteration":952,"passed_time":1.198155726,"remaining_time":0.05909057619},
{"learn":[0.5637487947],"iteration":953,"passed_time":1.199339035,"remaining_time":0.05782976479},
{"learn":[0.5625148258],"iteration":954,"passed_time":1.200542409,"remaining_time":0.05657006117},
{"learn":[0.5607959247],"iteration":955,"passed_time":1.201872625,"remaining_time":0.05531631326},
{"learn":[0.5596222257],"iteration":956,"passed_time":1.203078302,"remaining_time":0.0540568098},
{"learn":[0.5583498297],"iteration":957,"passed_time":1.20426717,"remaining_time":0.0527966818},
{"learn":[0.5577884449],"iteration":958,"passed_time":1.20548234,"remaining_time":0.05153782683},
{"learn":[0.5558119832],"iteration":959,"passed_time":1.206906312,"remaining_time":0.05028776301},
{"learn":[0.5546582796],"iteration":960,"passed_time":1.208145129,"remaining_time":0.04902982312},
{"learn":[0.5541283747],"iteration":961,"passed_time":1.209385181,"remaining_time":0.04777197181},
{"learn":[0.5529748681],"iteration":962,"passed_time":1.210665695,"remaining_time":0.04651571208},
{"learn":[0.5526952709],"iteration":963,"passed_time":1.211881799,"remaining_time":0.04525699663},
{"learn":[0.5518017439],"iteration":964,"passed_time":1.213050768,"remaining_time":0.04399665998},
{"learn":[0.550995181],"iteration":965,"passed_time":1.214243594,"remaining_time":0.04273735217},
{"learn":[0.5501738703],"iteration":966,"passed_time":1.215547613,"remaining_time":0.04148197646},
{"learn":[0.5491798936],"iteration":967,"passed_time":1.217008208,"remaining_time":0.04023167631},
{"learn":[0.5483114629],"iteration":968,"passed_time":1.218164978,"remaining_time":0.0389712222},
{"learn":[0.5470643342],"iteration":969,"passed_time":1.219492069,"remaining_time":0.03771624957},
{"learn":[0.5452157382],"iteration":970,"passed_time":1.220770601,"remaining_time":0.03645967809},
{"learn":[0.543958009],"iteration":971,"passed_time":1.221974717,"remaining_time":0.03520091776},
{"learn":[0.5427887565],"iteration":972,"passed_time":1.22327126,"remaining_time":0.03394483456},
{"learn":[0.5419132761],"iteration":973,"passed_time":1.224503822,"remaining_time":0.03268696034},
{"learn":[0.5403343221],"iteration":974,"passed_time":1.225772553,"remaining_time":0.03143006547},
{"learn":[0.5387773771],"iteration":975,"passed_time":1.226958653,"remaining_time":0.03017111441},
{"learn":[0.5383789462],"iteration":976,"passed_time":1.228282673,"remaining_time":0.02891555934},
{"learn":[0.5374849857],"iteration":977,"passed_time":1.229565037,"remaining_time":0.0276589272},
{"learn":[0.5360457679],"iteration":978,"passed_time":1.230738308,"remaining_time":0.02639990241},
{"learn":[0.5356812945],"iteration":979,"passed_time":1.232102038,"remaining_time":0.02514493955},
{"learn":[0.5344737264],"iteration":980,"passed_time":1.233390418,"remaining_time":0.02388829556},
{"learn":[0.5331308656],"iteration":981,"passed_time":1.234818201,"remaining_time":0.02263414217},
{"learn":[0.5327761359],"iteration":982,"passed_time":1.236081978,"remaining_time":0.02137679921},
{"learn":[0.5312000788],"iteration":983,"passed_time":1.237380196,"remaining_time":0.02012000319},
{"learn":[0.5300994141],"iteration":984,"passed_time":1.238621929,"remaining_time":0.01886226287},
{"learn":[0.5290552518],"iteration":985,"passed_time":1.24008105,"remaining_time":0.01760764169},
{"learn":[0.5278921912],"iteration":986,"passed_time":1.241256857,"remaining_time":0.01634887451},
{"learn":[0.5264662448],"iteration":987,"passed_time":1.242411553,"remaining_time":0.01509001887},
{"learn":[0.5254039665],"iteration":988,"passed_time":1.243659081,"remaining_time":0.01383240636},
{"learn":[0.5245934627],"iteration":989,"passed_time":1.244809485,"remaining_time":0.01257383319},
{"learn":[0.5236676299],"iteration":990,"passed_time":1.245896788,"remaining_time":0.01131490524},
{"learn":[0.5225693565],"iteration":991,"passed_time":1.247105673,"remaining_time":0.01005730382},
{"learn":[0.5211228017],"iteration":992,"passed_time":1.248249368,"remaining_time":0.008799340965},
{"learn":[0.5190980064],"iteration":993,"passed_time":1.249404706,"remaining_time":0.007541678307},
{"learn":[0.5179068902],"iteration":994,"passed_time":1.251101219,"remaining_time":0.0062869408},
{"learn":[0.517444658],"iteration":995,"passed_time":1.252670988,"remaining_time":0.005030807181},
{"learn":[0.5170337761],"iteration":996,"passed_time":1.254016429,"remaining_time":0.003773369394},
{"learn":[0.5158582301],"iteration":997,"passed_time":1.255216322,"remaining_time":0.002515463572},
{"learn":[0.5147638241],"iteration":998,"passed_time":1.256424075,"remaining_time":0.001257681757},
{"learn":[0.5133722839],"iteration":999,"passed_time":1.257542775,"remaining_time":0}
]}